modules/powerup_reset.v
module powerup_reset(key, clk, rst);
parameter TICK = 15; // tick's delay 0..15
		
input wire key;
input wire clk;
output reg rst;
		
reg [3:0] tick_timer;

initial begin
	rst <= 1;
	tick_timer <= TICK;
end
	
always @(posedge clk) begin
	if (key) begin
		tick_timer <= TICK;
		rst <= 1;
	end else begin
		if (tick_timer==4'd0) begin
			rst <= 0;
		end else begin
			tick_timer <= tick_timer - 1'b1;
		end
	end
end

endmodule

ModuleTesterIcarus/testbench.v
module testbench();

reg clk;

reg key;

wire reset_sig;

powerup_reset RS_GEN(.key(key), .clk(clk), .rst(reset_sig));

initial
begin
    $dumpfile("bench.vcd");
    $dumpvars(0,testbench);

    $display("starting testbench!!!!");
	
	repeat (300) begin
		#10;
		clk <= 1;
		#10;
		clk <= 0; 
	end
	
    $display("finished OK!");
    $finish;
end

initial
begin
	#1900;
	key <= 1;
	#90;
	key <= 0;
end
	
endmodule

ModuleTesterIcarus/bench.vcd
$date
	Thu Apr 16 17:29:49 2015
$end
$version
	Icarus Verilog
$end
$timescale
	1s
$end
$scope module testbench $end
$var wire 1 ! reset_sig $end
$var reg 1 " clk $end
$var reg 1 # key $end
$scope module RS_GEN $end
$var wire 1 " clk $end
$var wire 1 # key $end
$var reg 1 ! rst $end
$var reg 4 $ tick_timer [3:0] $end
$upscope $end
$upscope $end
$enddefinitions $end
#0
$dumpvars
b1111 $
x#
x"
1!
$end
#10
b1110 $
1"
#20
0"
#30
b1101 $
1"
#40
0"
#50
b1100 $
1"
#60
0"
#70
b1011 $
1"
#80
0"
#90
b1010 $
1"
#100
0"
#110
b1001 $
1"
#120
0"
#130
b1000 $
1"
#140
0"
#150
b111 $
1"
#160
0"
#170
b110 $
1"
#180
0"
#190
b101 $
1"
#200
0"
#210
b100 $
1"
#220
0"
#230
b11 $
1"
#240
0"
#250
b10 $
1"
#260
0"
#270
b1 $
1"
#280
0"
#290
b0 $
1"
#300
0"
#310
0!
1"
