modules/svca.v
// not signed, symmetric max/2
module svca(clk, in, cv, signal_out); //
parameter WIDTH = 8; //

input wire clk;
input wire [(WIDTH-1):0] in, cv;
output reg [(WIDTH-1):0] signal_out;
reg signed [((WIDTH*2)-1):0] result;

wire signed [(WIDTH-1):0] s_in = in - 8'd128; // 0..255 -> signed -128..127
wire signed [(WIDTH-1):0] s_cv = cv >> 1;

always @(posedge clk)
begin
  result = s_in * s_cv;
  signal_out = 8'd128 - (result >>> 7);
end

endmodule

ModuleTesterIcarus/testbench.v
module testbench();

reg clk;
reg [7:0] in_sig;
reg [7:0] in_cv;

initial
begin
	in_sig <= 8'd0;
	in_cv <= 8'd0;
end

wire [7:0] signal_out;
svca vca(clk, in_sig, in_cv, signal_out);

initial
begin
    $dumpfile("bench.vcd");
    $dumpvars(0,testbench);

    $display("starting testbench!!!!");
	
	repeat (3000) begin
		#10;
		clk <= 1;
		#10;
		clk <= 0; 
	end
	
    $display("finished OK!");
    //$finish;
end

initial
begin
	repeat (300) begin
		#100;
		in_sig <= 8'd0;
		#100;
		in_sig <= 8'b11111111; 
	end
end

initial
begin
	repeat (1024) begin
		#80;
		in_cv <= in_cv + 1'b1;
	end
end

	
endmodule

ModuleTesterIcarus/bench.vcd
$date
	Sun Apr 19 19:38:12 2015
$end
$version
	Icarus Verilog
$end
$timescale
	1s
$end
$scope module testbench $end
$var wire 8 ! signal_out [7:0] $end
$var reg 1 " clk $end
$var reg 8 # in_cv [7:0] $end
$var reg 8 $ in_sig [7:0] $end
$scope module vca $end
$var wire 1 " clk $end
$var wire 8 % cv [7:0] $end
$var wire 8 & in [7:0] $end
$var wire 8 ' s_in [7:0] $end
$var wire 8 ( s_cv [7:0] $end
$var reg 16 ) result [15:0] $end
$var reg 8 * signal_out [7:0] $end
$upscope $end
$upscope $end
$enddefinitions $end
#0
$dumpvars
bx *
bx )
b0 (
b10000000 '
b0 &
b0 %
b0 $
b0 #
x"
bx !
$end
#10
b10000000 !
b10000000 *
b0 )
1"
#20
0"
#30
1"
#40
0"
#50
1"
#60
0"
#70
1"
#80
0"
b1 #
b1 %
#90
1"
#100
0"
#110
1"
#120
0"
#130
1"
#140
0"
#150
1"
#160
b1 (
0"
b10 #
b10 %
#170
b10000001 !
b10000001 *
b1111111110000000 )
1"
#180
0"
#190
1"
#200
b1111111 '
0"
b11111111 $
b11111111 &
#210
b10000000 !
b10000000 *
b1111111 )
1"
#220
0"
#230
1"
#240
0"
b11 #
b11 %
#250
1"
#260
0"
#270
1"
#280
0"
#290
1"
#300
b10000000 '
0"
b0 $
b0 &
#310
b10000001 !
b10000001 *
b1111111110000000 )
1"
#320
b10 (
0"
b100 #
b100 %
#330
b10000010 !
b10000010 *
b1111111100000000 )
1"
#340
0"
#350
1"
#360
0"
#370
1"
#380
0"
#390
1"
#400
b1111111 '
0"
b101 #
b101 %
b11111111 $
b11111111 &
#410
b1111111 !
b1111111 *
b11111110 )
1"
#420
0"
#430
1"
#440
0"
#450
1"
#460
0"
#470
1"
#480
b11 (
0"
b110 #
b110 %
#490
b1111110 !
b1111110 *
b101111101 )
1"
#500
b10000000 '
0"
b0 $
b0 &
#510
b10000011 !
b10000011 *
b1111111010000000 )
1"
#520
0"
#530
1"
#540
0"
#550
1"
#560
0"
b111 #
b111 %
#570
1"
#580
0"
#590
1"
#600
b1111111 '
0"
b11111111 $
b11111111 &
#610
b1111110 !
b1111110 *
b101111101 )
1"
#620
0"
#630
1"
#640
b100 (
0"
b1000 #
b1000 %
#650
b1111101 !
b1111101 *
b111111100 )
1"
#660
0"
#670
1"
#680
0"
#690
1"
#700
b10000000 '
0"
b0 $
b0 &
#710
b10000100 !
b10000100 *
b1111111000000000 )
1"
#720
0"
b1001 #
b1001 %
#730
1"
#740
0"
#750
1"
#760
0"
#770
1"
#780
0"
#790
1"
#800
b101 (
b1111111 '
0"
b1010 #
b1010 %
b11111111 $
b11111111 &
#810
b1111100 !
b1111100 *
b1001111011 )
1"
#820
0"
#830
1"
#840
0"
#850
1"
#860
0"
#870
1"
#880
0"
b1011 #
b1011 %
#890
1"
#900
b10000000 '
0"
b0 $
b0 &
#910
b10000101 !
b10000101 *
b1111110110000000 )
1"
#920
0"
#930
1"
#940
0"
#950
1"
#960
b110 (
0"
b1100 #
b1100 %
#970
b10000110 !
b10000110 *
b1111110100000000 )
1"
#980
0"
#990
1"
#1000
b1111111 '
0"
b11111111 $
b11111111 &
#1010
b1111011 !
b1111011 *
b1011111010 )
1"
#1020
0"
#1030
1"
#1040
0"
b1101 #
b1101 %
#1050
1"
#1060
0"
#1070
1"
#1080
0"
#1090
1"
#1100
b10000000 '
0"
b0 $
b0 &
#1110
b10000110 !
b10000110 *
b1111110100000000 )
1"
#1120
b111 (
0"
b1110 #
b1110 %
#1130
b10000111 !
b10000111 *
b1111110010000000 )
1"
#1140
0"
#1150
1"
#1160
0"
#1170
1"
#1180
0"
#1190
1"
#1200
b1111111 '
0"
b1111 #
b1111 %
b11111111 $
b11111111 &
#1210
b1111010 !
b1111010 *
b1101111001 )
1"
#1220
0"
#1230
1"
#1240
0"
#1250
1"
#1260
0"
#1270
1"
#1280
b1000 (
0"
b10000 #
b10000 %
#1290
b1111001 !
b1111001 *
b1111111000 )
1"
#1300
b10000000 '
0"
b0 $
b0 &
#1310
b10001000 !
b10001000 *
b1111110000000000 )
1"
#1320
0"
#1330
1"
#1340
0"
#1350
1"
#1360
0"
b10001 #
b10001 %
#1370
1"
#1380
0"
#1390
1"
#1400
b1111111 '
0"
b11111111 $
b11111111 &
#1410
b1111001 !
b1111001 *
b1111111000 )
1"
#1420
0"
#1430
1"
#1440
b1001 (
0"
b10010 #
b10010 %
#1450
b1111000 !
b1111000 *
b10001110111 )
1"
#1460
0"
#1470
1"
#1480
0"
#1490
1"
#1500
b10000000 '
0"
b0 $
b0 &
#1510
b10001001 !
b10001001 *
b1111101110000000 )
1"
#1520
0"
b10011 #
b10011 %
#1530
1"
#1540
0"
#1550
1"
#1560
0"
#1570
1"
#1580
0"
#1590
1"
#1600
b1010 (
b1111111 '
0"
b10100 #
b10100 %
b11111111 $
b11111111 &
#1610
b1110111 !
b1110111 *
b10011110110 )
1"
#1620
0"
#1630
1"
#1640
0"
#1650
1"
#1660
0"
#1670
1"
#1680
0"
b10101 #
b10101 %
#1690
1"
#1700
b10000000 '
0"
b0 $
b0 &
#1710
b10001010 !
b10001010 *
b1111101100000000 )
1"
#1720
0"
#1730
1"
#1740
0"
#1750
1"
#1760
b1011 (
0"
b10110 #
b10110 %
#1770
b10001011 !
b10001011 *
b1111101010000000 )
1"
#1780
0"
#1790
1"
#1800
b1111111 '
0"
b11111111 $
b11111111 &
#1810
b1110110 !
b1110110 *
b10101110101 )
1"
#1820
0"
#1830
1"
#1840
0"
b10111 #
b10111 %
#1850
1"
#1860
0"
#1870
1"
#1880
0"
#1890
1"
#1900
b10000000 '
0"
b0 $
b0 &
#1910
b10001011 !
b10001011 *
b1111101010000000 )
1"
#1920
b1100 (
0"
b11000 #
b11000 %
#1930
b10001100 !
b10001100 *
b1111101000000000 )
1"
#1940
0"
#1950
1"
#1960
0"
#1970
1"
#1980
0"
#1990
1"
#2000
b1111111 '
0"
b11001 #
b11001 %
b11111111 $
b11111111 &
#2010
b1110101 !
b1110101 *
b10111110100 )
1"
#2020
0"
#2030
1"
#2040
0"
#2050
1"
#2060
0"
#2070
1"
#2080
b1101 (
0"
b11010 #
b11010 %
#2090
b1110100 !
b1110100 *
b11001110011 )
1"
#2100
b10000000 '
0"
b0 $
b0 &
#2110
b10001101 !
b10001101 *
b1111100110000000 )
1"
#2120
0"
#2130
1"
#2140
0"
#2150
1"
#2160
0"
b11011 #
b11011 %
#2170
1"
#2180
0"
#2190
1"
#2200
b1111111 '
0"
b11111111 $
b11111111 &
#2210
b1110100 !
b1110100 *
b11001110011 )
1"
#2220
0"
#2230
1"
#2240
b1110 (
0"
b11100 #
b11100 %
#2250
b1110011 !
b1110011 *
b11011110010 )
1"
#2260
0"
#2270
1"
#2280
0"
#2290
1"
#2300
b10000000 '
0"
b0 $
b0 &
#2310
b10001110 !
b10001110 *
b1111100100000000 )
1"
#2320
0"
b11101 #
b11101 %
#2330
1"
#2340
0"
#2350
1"
#2360
0"
#2370
1"
#2380
0"
#2390
1"
#2400
b1111 (
b1111111 '
0"
b11110 #
b11110 %
b11111111 $
b11111111 &
#2410
b1110010 !
b1110010 *
b11101110001 )
1"
#2420
0"
#2430
1"
#2440
0"
#2450
1"
#2460
0"
#2470
1"
#2480
0"
b11111 #
b11111 %
#2490
1"
#2500
b10000000 '
0"
b0 $
b0 &
#2510
b10001111 !
b10001111 *
b1111100010000000 )
1"
#2520
0"
#2530
1"
#2540
0"
#2550
1"
#2560
b10000 (
0"
b100000 #
b100000 %
#2570
b10010000 !
b10010000 *
b1111100000000000 )
1"
#2580
0"
#2590
1"
#2600
b1111111 '
0"
b11111111 $
b11111111 &
#2610
b1110001 !
b1110001 *
b11111110000 )
1"
#2620
0"
#2630
1"
#2640
0"
b100001 #
b100001 %
#2650
1"
#2660
0"
#2670
1"
#2680
0"
#2690
1"
#2700
b10000000 '
0"
b0 $
b0 &
#2710
b10010000 !
b10010000 *
b1111100000000000 )
1"
#2720
b10001 (
0"
b100010 #
b100010 %
#2730
b10010001 !
b10010001 *
b1111011110000000 )
1"
#2740
0"
#2750
1"
#2760
0"
#2770
1"
#2780
0"
#2790
1"
#2800
b1111111 '
0"
b100011 #
b100011 %
b11111111 $
b11111111 &
#2810
b1110000 !
b1110000 *
b100001101111 )
1"
#2820
0"
#2830
1"
#2840
0"
#2850
1"
#2860
0"
#2870
1"
#2880
b10010 (
0"
b100100 #
b100100 %
#2890
b1101111 !
b1101111 *
b100011101110 )
1"
#2900
b10000000 '
0"
b0 $
b0 &
#2910
b10010010 !
b10010010 *
b1111011100000000 )
1"
#2920
0"
#2930
1"
#2940
0"
#2950
1"
#2960
0"
b100101 #
b100101 %
#2970
1"
#2980
0"
#2990
1"
#3000
b1111111 '
0"
b11111111 $
b11111111 &
#3010
b1101111 !
b1101111 *
b100011101110 )
1"
#3020
0"
#3030
1"
#3040
b10011 (
0"
b100110 #
b100110 %
#3050
b1101110 !
b1101110 *
b100101101101 )
1"
#3060
0"
#3070
1"
#3080
0"
#3090
1"
#3100
b10000000 '
0"
b0 $
b0 &
#3110
b10010011 !
b10010011 *
b1111011010000000 )
1"
#3120
0"
b100111 #
b100111 %
#3130
1"
#3140
0"
#3150
1"
#3160
0"
#3170
1"
#3180
0"
#3190
1"
#3200
b10100 (
b1111111 '
0"
b101000 #
b101000 %
b11111111 $
b11111111 &
#3210
b1101101 !
b1101101 *
b100111101100 )
1"
#3220
0"
#3230
1"
#3240
0"
#3250
1"
#3260
0"
#3270
1"
#3280
0"
b101001 #
b101001 %
#3290
1"
#3300
b10000000 '
0"
b0 $
b0 &
#3310
b10010100 !
b10010100 *
b1111011000000000 )
1"
#3320
0"
#3330
1"
#3340
0"
#3350
1"
#3360
b10101 (
0"
b101010 #
b101010 %
#3370
b10010101 !
b10010101 *
b1111010110000000 )
1"
#3380
0"
#3390
1"
#3400
b1111111 '
0"
b11111111 $
b11111111 &
#3410
b1101100 !
b1101100 *
b101001101011 )
1"
#3420
0"
#3430
1"
#3440
0"
b101011 #
b101011 %
#3450
1"
#3460
0"
#3470
1"
#3480
0"
#3490
1"
#3500
b10000000 '
0"
b0 $
b0 &
#3510
b10010101 !
b10010101 *
b1111010110000000 )
1"
#3520
b10110 (
0"
b101100 #
b101100 %
#3530
b10010110 !
b10010110 *
b1111010100000000 )
1"
#3540
0"
#3550
1"
#3560
0"
#3570
1"
#3580
0"
#3590
1"
#3600
b1111111 '
0"
b101101 #
b101101 %
b11111111 $
b11111111 &
#3610
b1101011 !
b1101011 *
b101011101010 )
1"
#3620
0"
#3630
1"
#3640
0"
#3650
1"
#3660
0"
#3670
1"
#3680
b10111 (
0"
b101110 #
b101110 %
#3690
b1101010 !
b1101010 *
b101101101001 )
1"
#3700
b10000000 '
0"
b0 $
b0 &
#3710
b10010111 !
b10010111 *
b1111010010000000 )
1"
#3720
0"
#3730
1"
#3740
0"
#3750
1"
#3760
0"
b101111 #
b101111 %
#3770
1"
#3780
0"
#3790
1"
#3800
b1111111 '
0"
b11111111 $
b11111111 &
#3810
b1101010 !
b1101010 *
b101101101001 )
1"
#3820
0"
#3830
1"
#3840
b11000 (
0"
b110000 #
b110000 %
#3850
b1101001 !
b1101001 *
b101111101000 )
1"
#3860
0"
#3870
1"
#3880
0"
#3890
1"
#3900
b10000000 '
0"
b0 $
b0 &
#3910
b10011000 !
b10011000 *
b1111010000000000 )
1"
#3920
0"
b110001 #
b110001 %
#3930
1"
#3940
0"
#3950
1"
#3960
0"
#3970
1"
#3980
0"
#3990
1"
#4000
b11001 (
b1111111 '
0"
b110010 #
b110010 %
b11111111 $
b11111111 &
#4010
b1101000 !
b1101000 *
b110001100111 )
1"
#4020
0"
#4030
1"
#4040
0"
#4050
1"
#4060
0"
#4070
1"
#4080
0"
b110011 #
b110011 %
#4090
1"
#4100
b10000000 '
0"
b0 $
b0 &
#4110
b10011001 !
b10011001 *
b1111001110000000 )
1"
#4120
0"
#4130
1"
#4140
0"
#4150
1"
#4160
b11010 (
0"
b110100 #
b110100 %
#4170
b10011010 !
b10011010 *
b1111001100000000 )
1"
#4180
0"
#4190
1"
#4200
b1111111 '
0"
b11111111 $
b11111111 &
#4210
b1100111 !
b1100111 *
b110011100110 )
1"
#4220
0"
#4230
1"
#4240
0"
b110101 #
b110101 %
#4250
1"
#4260
0"
#4270
1"
#4280
0"
#4290
1"
#4300
b10000000 '
0"
b0 $
b0 &
#4310
b10011010 !
b10011010 *
b1111001100000000 )
1"
#4320
b11011 (
0"
b110110 #
b110110 %
#4330
b10011011 !
b10011011 *
b1111001010000000 )
1"
#4340
0"
#4350
1"
#4360
0"
#4370
1"
#4380
0"
#4390
1"
#4400
b1111111 '
0"
b110111 #
b110111 %
b11111111 $
b11111111 &
#4410
b1100110 !
b1100110 *
b110101100101 )
1"
#4420
0"
#4430
1"
#4440
0"
#4450
1"
#4460
0"
#4470
1"
#4480
b11100 (
0"
b111000 #
b111000 %
#4490
b1100101 !
b1100101 *
b110111100100 )
1"
#4500
b10000000 '
0"
b0 $
b0 &
#4510
b10011100 !
b10011100 *
b1111001000000000 )
1"
#4520
0"
#4530
1"
#4540
0"
#4550
1"
#4560
0"
b111001 #
b111001 %
#4570
1"
#4580
0"
#4590
1"
#4600
b1111111 '
0"
b11111111 $
b11111111 &
#4610
b1100101 !
b1100101 *
b110111100100 )
1"
#4620
0"
#4630
1"
#4640
b11101 (
0"
b111010 #
b111010 %
#4650
b1100100 !
b1100100 *
b111001100011 )
1"
#4660
0"
#4670
1"
#4680
0"
#4690
1"
#4700
b10000000 '
0"
b0 $
b0 &
#4710
b10011101 !
b10011101 *
b1111000110000000 )
1"
#4720
0"
b111011 #
b111011 %
#4730
1"
#4740
0"
#4750
1"
#4760
0"
#4770
1"
#4780
0"
#4790
1"
#4800
b11110 (
b1111111 '
0"
b111100 #
b111100 %
b11111111 $
b11111111 &
#4810
b1100011 !
b1100011 *
b111011100010 )
1"
#4820
0"
#4830
1"
#4840
0"
#4850
1"
#4860
0"
#4870
1"
#4880
0"
b111101 #
b111101 %
#4890
1"
#4900
b10000000 '
0"
b0 $
b0 &
#4910
b10011110 !
b10011110 *
b1111000100000000 )
1"
#4920
0"
#4930
1"
#4940
0"
#4950
1"
#4960
b11111 (
0"
b111110 #
b111110 %
#4970
b10011111 !
b10011111 *
b1111000010000000 )
1"
#4980
0"
#4990
1"
#5000
b1111111 '
0"
b11111111 $
b11111111 &
#5010
b1100010 !
b1100010 *
b111101100001 )
1"
#5020
0"
#5030
1"
#5040
0"
b111111 #
b111111 %
#5050
1"
#5060
0"
#5070
1"
#5080
0"
#5090
1"
#5100
b10000000 '
0"
b0 $
b0 &
#5110
b10011111 !
b10011111 *
b1111000010000000 )
1"
#5120
b100000 (
0"
b1000000 #
b1000000 %
#5130
b10100000 !
b10100000 *
b1111000000000000 )
1"
#5140
0"
#5150
1"
#5160
0"
#5170
1"
#5180
0"
#5190
1"
#5200
b1111111 '
0"
b1000001 #
b1000001 %
b11111111 $
b11111111 &
#5210
b1100001 !
b1100001 *
b111111100000 )
1"
#5220
0"
#5230
1"
#5240
0"
#5250
1"
#5260
0"
#5270
1"
#5280
b100001 (
0"
b1000010 #
b1000010 %
#5290
b1100000 !
b1100000 *
b1000001011111 )
1"
#5300
b10000000 '
0"
b0 $
b0 &
#5310
b10100001 !
b10100001 *
b1110111110000000 )
1"
#5320
0"
#5330
1"
#5340
0"
#5350
1"
#5360
0"
b1000011 #
b1000011 %
#5370
1"
#5380
0"
#5390
1"
#5400
b1111111 '
0"
b11111111 $
b11111111 &
#5410
b1100000 !
b1100000 *
b1000001011111 )
1"
#5420
0"
#5430
1"
#5440
b100010 (
0"
b1000100 #
b1000100 %
#5450
b1011111 !
b1011111 *
b1000011011110 )
1"
#5460
0"
#5470
1"
#5480
0"
#5490
1"
#5500
b10000000 '
0"
b0 $
b0 &
#5510
b10100010 !
b10100010 *
b1110111100000000 )
1"
#5520
0"
b1000101 #
b1000101 %
#5530
1"
#5540
0"
#5550
1"
#5560
0"
#5570
1"
#5580
0"
#5590
1"
#5600
b100011 (
b1111111 '
0"
b1000110 #
b1000110 %
b11111111 $
b11111111 &
#5610
b1011110 !
b1011110 *
b1000101011101 )
1"
#5620
0"
#5630
1"
#5640
0"
#5650
1"
#5660
0"
#5670
1"
#5680
0"
b1000111 #
b1000111 %
#5690
1"
#5700
b10000000 '
0"
b0 $
b0 &
#5710
b10100011 !
b10100011 *
b1110111010000000 )
1"
#5720
0"
#5730
1"
#5740
0"
#5750
1"
#5760
b100100 (
0"
b1001000 #
b1001000 %
#5770
b10100100 !
b10100100 *
b1110111000000000 )
1"
#5780
0"
#5790
1"
#5800
b1111111 '
0"
b11111111 $
b11111111 &
#5810
b1011101 !
b1011101 *
b1000111011100 )
1"
#5820
0"
#5830
1"
#5840
0"
b1001001 #
b1001001 %
#5850
1"
#5860
0"
#5870
1"
#5880
0"
#5890
1"
#5900
b10000000 '
0"
b0 $
b0 &
#5910
b10100100 !
b10100100 *
b1110111000000000 )
1"
#5920
b100101 (
0"
b1001010 #
b1001010 %
#5930
b10100101 !
b10100101 *
b1110110110000000 )
1"
#5940
0"
#5950
1"
#5960
0"
#5970
1"
#5980
0"
#5990
1"
#6000
b1111111 '
0"
b1001011 #
b1001011 %
b11111111 $
b11111111 &
#6010
b1011100 !
b1011100 *
b1001001011011 )
1"
#6020
0"
#6030
1"
#6040
0"
#6050
1"
#6060
0"
#6070
1"
#6080
b100110 (
0"
b1001100 #
b1001100 %
#6090
b1011011 !
b1011011 *
b1001011011010 )
1"
#6100
b10000000 '
0"
b0 $
b0 &
#6110
b10100110 !
b10100110 *
b1110110100000000 )
1"
#6120
0"
#6130
1"
#6140
0"
#6150
1"
#6160
0"
b1001101 #
b1001101 %
#6170
1"
#6180
0"
#6190
1"
#6200
b1111111 '
0"
b11111111 $
b11111111 &
#6210
b1011011 !
b1011011 *
b1001011011010 )
1"
#6220
0"
#6230
1"
#6240
b100111 (
0"
b1001110 #
b1001110 %
#6250
b1011010 !
b1011010 *
b1001101011001 )
1"
#6260
0"
#6270
1"
#6280
0"
#6290
1"
#6300
b10000000 '
0"
b0 $
b0 &
#6310
b10100111 !
b10100111 *
b1110110010000000 )
1"
#6320
0"
b1001111 #
b1001111 %
#6330
1"
#6340
0"
#6350
1"
#6360
0"
#6370
1"
#6380
0"
#6390
1"
#6400
b101000 (
b1111111 '
0"
b1010000 #
b1010000 %
b11111111 $
b11111111 &
#6410
b1011001 !
b1011001 *
b1001111011000 )
1"
#6420
0"
#6430
1"
#6440
0"
#6450
1"
#6460
0"
#6470
1"
#6480
0"
b1010001 #
b1010001 %
#6490
1"
#6500
b10000000 '
0"
b0 $
b0 &
#6510
b10101000 !
b10101000 *
b1110110000000000 )
1"
#6520
0"
#6530
1"
#6540
0"
#6550
1"
#6560
b101001 (
0"
b1010010 #
b1010010 %
#6570
b10101001 !
b10101001 *
b1110101110000000 )
1"
#6580
0"
#6590
1"
#6600
b1111111 '
0"
b11111111 $
b11111111 &
#6610
b1011000 !
b1011000 *
b1010001010111 )
1"
#6620
0"
#6630
1"
#6640
0"
b1010011 #
b1010011 %
#6650
1"
#6660
0"
#6670
1"
#6680
0"
#6690
1"
#6700
b10000000 '
0"
b0 $
b0 &
#6710
b10101001 !
b10101001 *
b1110101110000000 )
1"
#6720
b101010 (
0"
b1010100 #
b1010100 %
#6730
b10101010 !
b10101010 *
b1110101100000000 )
1"
#6740
0"
#6750
1"
#6760
0"
#6770
1"
#6780
0"
#6790
1"
#6800
b1111111 '
0"
b1010101 #
b1010101 %
b11111111 $
b11111111 &
#6810
b1010111 !
b1010111 *
b1010011010110 )
1"
#6820
0"
#6830
1"
#6840
0"
#6850
1"
#6860
0"
#6870
1"
#6880
b101011 (
0"
b1010110 #
b1010110 %
#6890
b1010110 !
b1010110 *
b1010101010101 )
1"
#6900
b10000000 '
0"
b0 $
b0 &
#6910
b10101011 !
b10101011 *
b1110101010000000 )
1"
#6920
0"
#6930
1"
#6940
0"
#6950
1"
#6960
0"
b1010111 #
b1010111 %
#6970
1"
#6980
0"
#6990
1"
#7000
b1111111 '
0"
b11111111 $
b11111111 &
#7010
b1010110 !
b1010110 *
b1010101010101 )
1"
#7020
0"
#7030
1"
#7040
b101100 (
0"
b1011000 #
b1011000 %
#7050
b1010101 !
b1010101 *
b1010111010100 )
1"
#7060
0"
#7070
1"
#7080
0"
#7090
1"
#7100
b10000000 '
0"
b0 $
b0 &
#7110
b10101100 !
b10101100 *
b1110101000000000 )
1"
#7120
0"
b1011001 #
b1011001 %
#7130
1"
#7140
0"
#7150
1"
#7160
0"
#7170
1"
#7180
0"
#7190
1"
#7200
b101101 (
b1111111 '
0"
b1011010 #
b1011010 %
b11111111 $
b11111111 &
#7210
b1010100 !
b1010100 *
b1011001010011 )
1"
#7220
0"
#7230
1"
#7240
0"
#7250
1"
#7260
0"
#7270
1"
#7280
0"
b1011011 #
b1011011 %
#7290
1"
#7300
b10000000 '
0"
b0 $
b0 &
#7310
b10101101 !
b10101101 *
b1110100110000000 )
1"
#7320
0"
#7330
1"
#7340
0"
#7350
1"
#7360
b101110 (
0"
b1011100 #
b1011100 %
#7370
b10101110 !
b10101110 *
b1110100100000000 )
1"
#7380
0"
#7390
1"
#7400
b1111111 '
0"
b11111111 $
b11111111 &
#7410
b1010011 !
b1010011 *
b1011011010010 )
1"
#7420
0"
#7430
1"
#7440
0"
b1011101 #
b1011101 %
#7450
1"
#7460
0"
#7470
1"
#7480
0"
#7490
1"
#7500
b10000000 '
0"
b0 $
b0 &
#7510
b10101110 !
b10101110 *
b1110100100000000 )
1"
#7520
b101111 (
0"
b1011110 #
b1011110 %
#7530
b10101111 !
b10101111 *
b1110100010000000 )
1"
#7540
0"
#7550
1"
#7560
0"
#7570
1"
#7580
0"
#7590
1"
#7600
b1111111 '
0"
b1011111 #
b1011111 %
b11111111 $
b11111111 &
#7610
b1010010 !
b1010010 *
b1011101010001 )
1"
#7620
0"
#7630
1"
#7640
0"
#7650
1"
#7660
0"
#7670
1"
#7680
b110000 (
0"
b1100000 #
b1100000 %
#7690
b1010001 !
b1010001 *
b1011111010000 )
1"
#7700
b10000000 '
0"
b0 $
b0 &
#7710
b10110000 !
b10110000 *
b1110100000000000 )
1"
#7720
0"
#7730
1"
#7740
0"
#7750
1"
#7760
0"
b1100001 #
b1100001 %
#7770
1"
#7780
0"
#7790
1"
#7800
b1111111 '
0"
b11111111 $
b11111111 &
#7810
b1010001 !
b1010001 *
b1011111010000 )
1"
#7820
0"
#7830
1"
#7840
b110001 (
0"
b1100010 #
b1100010 %
#7850
b1010000 !
b1010000 *
b1100001001111 )
1"
#7860
0"
#7870
1"
#7880
0"
#7890
1"
#7900
b10000000 '
0"
b0 $
b0 &
#7910
b10110001 !
b10110001 *
b1110011110000000 )
1"
#7920
0"
b1100011 #
b1100011 %
#7930
1"
#7940
0"
#7950
1"
#7960
0"
#7970
1"
#7980
0"
#7990
1"
#8000
b110010 (
b1111111 '
0"
b1100100 #
b1100100 %
b11111111 $
b11111111 &
#8010
b1001111 !
b1001111 *
b1100011001110 )
1"
#8020
0"
#8030
1"
#8040
0"
#8050
1"
#8060
0"
#8070
1"
#8080
0"
b1100101 #
b1100101 %
#8090
1"
#8100
b10000000 '
0"
b0 $
b0 &
#8110
b10110010 !
b10110010 *
b1110011100000000 )
1"
#8120
0"
#8130
1"
#8140
0"
#8150
1"
#8160
b110011 (
0"
b1100110 #
b1100110 %
#8170
b10110011 !
b10110011 *
b1110011010000000 )
1"
#8180
0"
#8190
1"
#8200
b1111111 '
0"
b11111111 $
b11111111 &
#8210
b1001110 !
b1001110 *
b1100101001101 )
1"
#8220
0"
#8230
1"
#8240
0"
b1100111 #
b1100111 %
#8250
1"
#8260
0"
#8270
1"
#8280
0"
#8290
1"
#8300
b10000000 '
0"
b0 $
b0 &
#8310
b10110011 !
b10110011 *
b1110011010000000 )
1"
#8320
b110100 (
0"
b1101000 #
b1101000 %
#8330
b10110100 !
b10110100 *
b1110011000000000 )
1"
#8340
0"
#8350
1"
#8360
0"
#8370
1"
#8380
0"
#8390
1"
#8400
b1111111 '
0"
b1101001 #
b1101001 %
b11111111 $
b11111111 &
#8410
b1001101 !
b1001101 *
b1100111001100 )
1"
#8420
0"
#8430
1"
#8440
0"
#8450
1"
#8460
0"
#8470
1"
#8480
b110101 (
0"
b1101010 #
b1101010 %
#8490
b1001100 !
b1001100 *
b1101001001011 )
1"
#8500
b10000000 '
0"
b0 $
b0 &
#8510
b10110101 !
b10110101 *
b1110010110000000 )
1"
#8520
0"
#8530
1"
#8540
0"
#8550
1"
#8560
0"
b1101011 #
b1101011 %
#8570
1"
#8580
0"
#8590
1"
#8600
b1111111 '
0"
b11111111 $
b11111111 &
#8610
b1001100 !
b1001100 *
b1101001001011 )
1"
#8620
0"
#8630
1"
#8640
b110110 (
0"
b1101100 #
b1101100 %
#8650
b1001011 !
b1001011 *
b1101011001010 )
1"
#8660
0"
#8670
1"
#8680
0"
#8690
1"
#8700
b10000000 '
0"
b0 $
b0 &
#8710
b10110110 !
b10110110 *
b1110010100000000 )
1"
#8720
0"
b1101101 #
b1101101 %
#8730
1"
#8740
0"
#8750
1"
#8760
0"
#8770
1"
#8780
0"
#8790
1"
#8800
b110111 (
b1111111 '
0"
b1101110 #
b1101110 %
b11111111 $
b11111111 &
#8810
b1001010 !
b1001010 *
b1101101001001 )
1"
#8820
0"
#8830
1"
#8840
0"
#8850
1"
#8860
0"
#8870
1"
#8880
0"
b1101111 #
b1101111 %
#8890
1"
#8900
b10000000 '
0"
b0 $
b0 &
#8910
b10110111 !
b10110111 *
b1110010010000000 )
1"
#8920
0"
#8930
1"
#8940
0"
#8950
1"
#8960
b111000 (
0"
b1110000 #
b1110000 %
#8970
b10111000 !
b10111000 *
b1110010000000000 )
1"
#8980
0"
#8990
1"
#9000
b1111111 '
0"
b11111111 $
b11111111 &
#9010
b1001001 !
b1001001 *
b1101111001000 )
1"
#9020
0"
#9030
1"
#9040
0"
b1110001 #
b1110001 %
#9050
1"
#9060
0"
#9070
1"
#9080
0"
#9090
1"
#9100
b10000000 '
0"
b0 $
b0 &
#9110
b10111000 !
b10111000 *
b1110010000000000 )
1"
#9120
b111001 (
0"
b1110010 #
b1110010 %
#9130
b10111001 !
b10111001 *
b1110001110000000 )
1"
#9140
0"
#9150
1"
#9160
0"
#9170
1"
#9180
0"
#9190
1"
#9200
b1111111 '
0"
b1110011 #
b1110011 %
b11111111 $
b11111111 &
#9210
b1001000 !
b1001000 *
b1110001000111 )
1"
#9220
0"
#9230
1"
#9240
0"
#9250
1"
#9260
0"
#9270
1"
#9280
b111010 (
0"
b1110100 #
b1110100 %
#9290
b1000111 !
b1000111 *
b1110011000110 )
1"
#9300
b10000000 '
0"
b0 $
b0 &
#9310
b10111010 !
b10111010 *
b1110001100000000 )
1"
#9320
0"
#9330
1"
#9340
0"
#9350
1"
#9360
0"
b1110101 #
b1110101 %
#9370
1"
#9380
0"
#9390
1"
#9400
b1111111 '
0"
b11111111 $
b11111111 &
#9410
b1000111 !
b1000111 *
b1110011000110 )
1"
#9420
0"
#9430
1"
#9440
b111011 (
0"
b1110110 #
b1110110 %
#9450
b1000110 !
b1000110 *
b1110101000101 )
1"
#9460
0"
#9470
1"
#9480
0"
#9490
1"
#9500
b10000000 '
0"
b0 $
b0 &
#9510
b10111011 !
b10111011 *
b1110001010000000 )
1"
#9520
0"
b1110111 #
b1110111 %
#9530
1"
#9540
0"
#9550
1"
#9560
0"
#9570
1"
#9580
0"
#9590
1"
#9600
b111100 (
b1111111 '
0"
b1111000 #
b1111000 %
b11111111 $
b11111111 &
#9610
b1000101 !
b1000101 *
b1110111000100 )
1"
#9620
0"
#9630
1"
#9640
0"
#9650
1"
#9660
0"
#9670
1"
#9680
0"
b1111001 #
b1111001 %
#9690
1"
#9700
b10000000 '
0"
b0 $
b0 &
#9710
b10111100 !
b10111100 *
b1110001000000000 )
1"
#9720
0"
#9730
1"
#9740
0"
#9750
1"
#9760
b111101 (
0"
b1111010 #
b1111010 %
#9770
b10111101 !
b10111101 *
b1110000110000000 )
1"
#9780
0"
#9790
1"
#9800
b1111111 '
0"
b11111111 $
b11111111 &
#9810
b1000100 !
b1000100 *
b1111001000011 )
1"
#9820
0"
#9830
1"
#9840
0"
b1111011 #
b1111011 %
#9850
1"
#9860
0"
#9870
1"
