benches/fifo/fifo.v
module fifo(in_data, in_d_rdy, clk, out_data, out_d_rdy, rdy2rcv);
parameter WIDTH=8;
					   
parameter BUFF_LEN=16;
parameter BUFF_LENm=BUFF_LEN - 1;

parameter BUFF_LEN_WIDTH_bits  = (BUFF_LENm[7:7]==1'b1) ? 8 : 
					   (BUFF_LENm[6:6]==1'b1) ? 7 :
					   (BUFF_LENm[5:5]==1'b1) ? 6 :
					   (BUFF_LENm[4:4]==1'b1) ? 5 :
					   (BUFF_LENm[3:3]==1'b1) ? 4 :
					   (BUFF_LENm[2:2]==1'b1) ? 3 :
					   (BUFF_LENm[1:1]==1'b1) ? 2 :
					   (BUFF_LENm[0:0]==1'b1) ? 1 : 0;

input wire [(WIDTH-1):0] in_data;
input wire in_d_rdy, clk, rdy2rcv;
output wire [(WIDTH-1):0] out_data;
output wire out_d_rdy;

//fifo

reg [(BUFF_LEN_WIDTH_bits-1):0] fifo_buff_wptr;
initial fifo_buff_wptr <= {BUFF_LEN_WIDTH_bits {1'b0}};
reg [(BUFF_LEN_WIDTH_bits-1):0] fifo_buff_sptr;
initial fifo_buff_sptr <= {BUFF_LEN_WIDTH_bits {1'b0}};
reg [(BUFF_LEN_WIDTH_bits-1):0] fifo_buff_cnt;
initial fifo_buff_cnt <= {BUFF_LEN_WIDTH_bits {1'b0}};
reg [(WIDTH-1):0] fifo_buff [0:(BUFF_LEN-1)];

integer i;
initial begin
	for(i=0;i<BUFF_LEN;i=i+1) begin 
		fifo_buff[i] <= {WIDTH {1'b0}};
	end
end

assign out_d_rdy = (fifo_buff_cnt>0)&&rdy2rcv;
assign out_data = (out_d_rdy) ? fifo_buff[fifo_buff_sptr] : {WIDTH {1'b0}};
//assign out_data = fifo_buff[fifo_buff_sptr];

always @ (posedge clk) begin
	if (in_d_rdy==1'b1) begin //in_d_rdy - store
		fifo_buff[fifo_buff_wptr] <= in_data;
		fifo_buff_wptr <= fifo_buff_wptr + 1'b1;
		if ((fifo_buff_cnt!={BUFF_LEN_WIDTH_bits {1'b0}})&&(rdy2rcv==1'b1)) begin
			fifo_buff_sptr <= fifo_buff_sptr + 1'b1;
			fifo_buff_cnt <= fifo_buff_cnt; 
		end else begin
			fifo_buff_cnt <= fifo_buff_cnt + 1'b1;
		end
	end else begin // restore data only when not write data
		if ((fifo_buff_cnt!={BUFF_LEN_WIDTH_bits {1'b0}})&&(rdy2rcv==1'b1)) begin
			fifo_buff_sptr <= fifo_buff_sptr + 1'b1;
			fifo_buff_cnt <= fifo_buff_cnt - 1'b1;
		end
	end

end
	
endmodule

benches/fifo/testbench.v
module testbench();

reg clk;
reg [7:0] in_data;
reg in_d_rdy;
reg rdy2rcv;
reg rdy2rcv_b;

wire [7:0] out_data;
wire out_d_rdy;

fifo buff01(.clk(clk), .in_data(in_data), .in_d_rdy(in_d_rdy), .rdy2rcv(rdy2rcv_b),
			.out_data(out_data), .out_d_rdy(out_d_rdy));

initial begin
    $dumpfile("bench.vcd");
    $dumpvars(0,testbench);

    $display("starting testbench!!!!");
	
	
	clk <= 0; 
	repeat (3000) begin
		#10;
		clk <= 1;
		#10;
		clk <= 0; 
	end
	
    $display("finished OK!");
    $finish;
end

initial begin
	in_data <= 8'd0;
	in_d_rdy <= 0;
	repeat (20) begin
		#200;
		in_d_rdy <= 1;
		in_data <= in_data + 1'b1;
		#20;
		in_d_rdy <= 0;
	end
	in_data <= 8'd0;
	in_d_rdy <= 0;	
end

always @(posedge clk) rdy2rcv_b<=rdy2rcv;

initial begin
	rdy2rcv <= 1;
	#1100;
	rdy2rcv <= 0;
	#1000;
	rdy2rcv <= 1;
	#1000;
	rdy2rcv <= 0;
	#2000;
	rdy2rcv <= 1;
end
	
endmodule

benches/fifo/bench.vcd
$date
	Sat Aug 15 02:49:40 2015
$end
$version
	Icarus Verilog
$end
$timescale
	1s
$end
$scope module testbench $end
$var wire 8 ! out_data [7:0] $end
$var wire 1 " out_d_rdy $end
$var reg 1 # clk $end
$var reg 1 $ in_d_rdy $end
$var reg 8 % in_data [7:0] $end
$var reg 1 & rdy2rcv $end
$var reg 1 ' rdy2rcv_b $end
$scope module buff01 $end
$var wire 1 # clk $end
$var wire 1 $ in_d_rdy $end
$var wire 8 ( in_data [7:0] $end
$var wire 1 " out_d_rdy $end
$var wire 1 ' rdy2rcv $end
$var wire 8 ) out_data [7:0] $end
$var reg 4 * fifo_buff_cnt [3:0] $end
$var reg 4 + fifo_buff_sptr [3:0] $end
$var reg 4 , fifo_buff_wptr [3:0] $end
$var integer 32 - i [31:0] $end
$upscope $end
$upscope $end
$enddefinitions $end
#0
$dumpvars
b10000 -
b0 ,
b0 +
b0 *
b0 )
b0 (
x'
1&
b0 %
0$
0#
0"
b0 !
$end
#10
1'
1#
#20
0#
#30
1#
#40
0#
#50
1#
#60
0#
#70
1#
#80
0#
#90
1#
#100
0#
#110
1#
#120
0#
#130
1#
#140
0#
#150
1#
#160
0#
#170
1#
#180
0#
#190
1#
#200
0#
b1 %
b1 (
1$
#210
b1 !
b1 )
1"
b1 *
b1 ,
1#
#220
0#
0$
#230
0"
b0 !
b0 )
b0 *
b1 +
1#
#240
0#
#250
1#
#260
0#
#270
1#
#280
0#
#290
1#
#300
0#
#310
1#
#320
0#
#330
1#
#340
0#
#350
1#
#360
0#
#370
1#
#380
0#
#390
1#
#400
0#
#410
1#
#420
0#
b10 %
b10 (
1$
#430
b10 !
b10 )
1"
b1 *
b10 ,
1#
#440
0#
0$
#450
0"
b0 !
b0 )
b0 *
b10 +
1#
#460
0#
#470
1#
#480
0#
#490
1#
#500
0#
#510
1#
#520
0#
#530
1#
#540
0#
#550
1#
#560
0#
#570
1#
#580
0#
#590
1#
#600
0#
#610
1#
#620
0#
#630
1#
#640
0#
b11 %
b11 (
1$
#650
b11 !
b11 )
1"
b1 *
b11 ,
1#
#660
0#
0$
#670
0"
b0 !
b0 )
b0 *
b11 +
1#
#680
0#
#690
1#
#700
0#
#710
1#
#720
0#
#730
1#
#740
0#
#750
1#
#760
0#
#770
1#
#780
0#
#790
1#
#800
0#
#810
1#
#820
0#
#830
1#
#840
0#
#850
1#
#860
0#
b100 %
b100 (
1$
#870
b100 !
b100 )
1"
b1 *
b100 ,
1#
#880
0#
0$
#890
0"
b0 !
b0 )
b0 *
b100 +
1#
#900
0#
#910
1#
#920
0#
#930
1#
#940
0#
#950
1#
#960
0#
#970
1#
#980
0#
#990
1#
#1000
0#
#1010
1#
#1020
0#
#1030
1#
#1040
0#
#1050
1#
#1060
0#
#1070
1#
#1080
0#
b101 %
b101 (
1$
#1090
b101 !
b101 )
1"
b1 *
b101 ,
1#
#1100
0#
0$
0&
#1110
0"
b0 !
b0 )
0'
b0 *
b101 +
1#
#1120
0#
#1130
1#
#1140
0#
#1150
1#
#1160
0#
#1170
1#
#1180
0#
#1190
1#
#1200
0#
#1210
1#
#1220
0#
#1230
1#
#1240
0#
#1250
1#
#1260
0#
#1270
1#
#1280
0#
#1290
1#
#1300
0#
b110 %
b110 (
1$
#1310
b1 *
b110 ,
1#
#1320
0#
0$
#1330
1#
#1340
0#
#1350
1#
#1360
0#
#1370
1#
#1380
0#
#1390
1#
#1400
0#
#1410
1#
#1420
0#
#1430
1#
#1440
0#
#1450
1#
#1460
0#
#1470
1#
#1480
0#
#1490
1#
#1500
0#
#1510
1#
#1520
0#
b111 %
b111 (
1$
#1530
b10 *
b111 ,
1#
#1540
0#
0$
#1550
1#
#1560
0#
#1570
1#
#1580
0#
#1590
1#
#1600
0#
#1610
1#
#1620
0#
#1630
1#
#1640
0#
#1650
1#
#1660
0#
#1670
1#
#1680
0#
#1690
1#
#1700
0#
#1710
1#
#1720
0#
#1730
1#
#1740
0#
b1000 %
b1000 (
1$
#1750
b11 *
b1000 ,
1#
#1760
0#
0$
#1770
1#
#1780
0#
#1790
1#
#1800
0#
#1810
1#
#1820
0#
#1830
1#
#1840
0#
#1850
1#
#1860
0#
#1870
1#
#1880
0#
#1890
1#
#1900
0#
#1910
1#
#1920
0#
#1930
1#
#1940
0#
#1950
1#
#1960
0#
b1001 %
b1001 (
1$
#1970
b100 *
b1001 ,
1#
#1980
0#
0$
#1990
1#
#2000
0#
#2010
1#
#2020
0#
#2030
1#
#2040
0#
#2050
1#
#2060
0#
#2070
1#
#2080
0#
#2090
1#
#2100
0#
1&
#2110
b110 !
b110 )
1"
1'
1#
#2120
0#
#2130
b111 !
b111 )
b11 *
b110 +
1#
#2140
0#
#2150
b1000 !
b1000 )
b10 *
b111 +
1#
#2160
0#
#2170
b1001 !
b1001 )
b1 *
b1000 +
1#
#2180
0#
b1010 %
b1010 (
1$
#2190
b1010 !
b1010 )
b1001 +
b1010 ,
1#
#2200
0#
0$
#2210
0"
b0 !
b0 )
b0 *
b1010 +
1#
#2220
0#
#2230
1#
#2240
0#
#2250
1#
#2260
0#
#2270
1#
#2280
0#
#2290
1#
#2300
0#
#2310
1#
#2320
0#
#2330
1#
#2340
0#
#2350
1#
#2360
0#
#2370
1#
#2380
0#
#2390
1#
#2400
0#
b1011 %
b1011 (
1$
#2410
b1011 !
b1011 )
1"
b1 *
b1011 ,
1#
#2420
0#
0$
#2430
0"
b0 !
b0 )
b0 *
b1011 +
1#
#2440
0#
#2450
1#
#2460
0#
#2470
1#
#2480
0#
#2490
1#
#2500
0#
#2510
1#
#2520
0#
#2530
1#
#2540
0#
#2550
1#
#2560
0#
#2570
1#
#2580
0#
#2590
1#
#2600
0#
#2610
1#
#2620
0#
b1100 %
b1100 (
1$
#2630
b1100 !
b1100 )
1"
b1 *
b1100 ,
1#
#2640
0#
0$
#2650
0"
b0 !
b0 )
b0 *
b1100 +
1#
#2660
0#
#2670
1#
#2680
0#
#2690
1#
#2700
0#
#2710
1#
#2720
0#
#2730
1#
#2740
0#
#2750
1#
#2760
0#
#2770
1#
#2780
0#
#2790
1#
#2800
0#
#2810
1#
#2820
0#
#2830
1#
#2840
0#
b1101 %
b1101 (
1$
#2850
b1101 !
b1101 )
1"
b1 *
b1101 ,
1#
#2860
0#
0$
#2870
0"
b0 !
b0 )
b0 *
b1101 +
1#
#2880
0#
#2890
1#
#2900
0#
#2910
1#
#2920
0#
#2930
1#
#2940
0#
#2950
1#
#2960
0#
#2970
1#
#2980
0#
#2990
1#
#3000
0#
#3010
1#
#3020
0#
#3030
1#
#3040
0#
#3050
1#
#3060
0#
b1110 %
b1110 (
1$
#3070
b1110 !
b1110 )
1"
b1 *
b1110 ,
1#
#3080
0#
0$
#3090
0"
b0 !
b0 )
b0 *
b1110 +
1#
#3100
0#
0&
#3110
0'
1#
#3120
0#
#3130
1#
#3140
0#
#3150
1#
#3160
0#
#3170
1#
#3180
0#
#3190
1#
#3200
0#
#3210
1#
#3220
0#
#3230
1#
#3240
0#
#3250
1#
#3260
0#
#3270
1#
#3280
0#
b1111 %
b1111 (
1$
#3290
b1 *
b1111 ,
1#
#3300
0#
0$
#3310
1#
#3320
0#
#3330
1#
#3340
0#
#3350
1#
#3360
0#
#3370
1#
#3380
0#
#3390
1#
#3400
0#
#3410
1#
#3420
0#
#3430
1#
#3440
0#
#3450
1#
#3460
0#
#3470
1#
#3480
0#
#3490
1#
#3500
0#
b10000 %
b10000 (
1$
#3510
b10 *
b0 ,
1#
#3520
0#
0$
#3530
1#
#3540
0#
#3550
1#
#3560
0#
#3570
1#
#3580
0#
#3590
1#
#3600
0#
#3610
1#
#3620
0#
#3630
1#
#3640
0#
#3650
1#
#3660
0#
#3670
1#
#3680
0#
#3690
1#
#3700
0#
#3710
1#
#3720
0#
b10001 %
b10001 (
1$
#3730
b11 *
b1 ,
1#
#3740
0#
0$
#3750
1#
#3760
0#
#3770
1#
#3780
0#
#3790
1#
#3800
0#
#3810
1#
#3820
0#
#3830
1#
#3840
0#
#3850
1#
#3860
0#
#3870
1#
#3880
0#
#3890
1#
#3900
0#
#3910
1#
#3920
0#
#3930
1#
#3940
0#
b10010 %
b10010 (
1$
#3950
b100 *
b10 ,
1#
#3960
0#
0$
#3970
1#
#3980
0#
#3990
1#
#4000
0#
#4010
1#
#4020
0#
#4030
1#
#4040
0#
#4050
1#
#4060
0#
#4070
1#
#4080
0#
#4090
1#
#4100
0#
#4110
1#
#4120
0#
#4130
1#
#4140
0#
#4150
1#
#4160
0#
b10011 %
b10011 (
1$
#4170
b101 *
b11 ,
1#
#4180
0#
0$
#4190
1#
#4200
0#
#4210
1#
#4220
0#
#4230
1#
#4240
0#
#4250
1#
#4260
0#
#4270
1#
#4280
0#
#4290
1#
#4300
0#
#4310
1#
#4320
0#
#4330
1#
#4340
0#
#4350
1#
#4360
0#
#4370
1#
#4380
0#
b10100 %
b10100 (
1$
#4390
b110 *
b100 ,
1#
#4400
0#
b0 %
b0 (
0$
