benches/i2s_tx/frqdivmod.v
module frqdivmod(clk, s_out);
parameter DIV=2;
// calculated parameters
parameter WITH = ($clog2(DIV+1)>0) ? $clog2(DIV+1) : 1;

input wire clk;
output wire s_out;

reg clk_n; 

reg [(WITH-1):0] pos_cnt; 
reg [(WITH-1):0] neg_cnt; 

wire [(WITH-1):0] div_value = DIV[(WITH-1):0];

//div2 - 0  -- 1
//div4 - 1     2
//div6 - 2     3
//div8 - 3     4
initial begin
	clk_n <= 1'b0;
	pos_cnt <= {(WITH){1'b0}} + (DIV/2 - 1);
	neg_cnt <= {(WITH){1'b0}};
end

assign s_out = (DIV==1) ? clk : clk_n;

always @ (posedge clk) begin
	pos_cnt <= (pos_cnt + 1'b1) % div_value;
end

always @ (negedge clk) begin
	neg_cnt <= (neg_cnt + 1'b1) % div_value;
end

always @(clk, pos_cnt, neg_cnt) begin //pos_cnt in sens list addd for resolve warning "variable is read inside the Always Construct but isn't in the Always Construct's Event Control"
	if ((DIV%2) == 1'b0) begin
		clk_n <= ( pos_cnt >= (DIV/2)) ? 1'b1 : 1'b0;
	end else begin
		clk_n <= (( pos_cnt > (DIV/2)) || ( neg_cnt > (DIV/2))) ? 1'b1 : 1'b0;
	end
end
	
endmodule

benches/frqdivmod/testbench.v
module testbench();

reg tb_clk;

wire out_val;
frqdivmod #(.DIV(3)) div1(tb_clk, out_val);

initial
begin
    $dumpfile("bench.vcd");
    $dumpvars(0,testbench);

    $display("starting testbench!!!!");
	$display("bits for 0..9", $clog2(1));
	
	tb_clk <= 0;
	repeat (20000) begin
		#1;
		tb_clk <= 1;
		#1;
		tb_clk <= 0;
	end
	
    $display("finished OK!");
    $finish;
end
	
endmodule

benches/frqdivmod/bench.vcd
$date
	Wed Oct 12 13:24:11 2016
$end
$version
	Icarus Verilog
$end
$timescale
	1s
$end
$scope module testbench $end
$var wire 1 ! out_val $end
$var reg 1 " tb_clk $end
$scope module div1 $end
$var wire 1 " clk $end
$var wire 2 # div_value [1:0] $end
$var wire 1 ! s_out $end
$var reg 1 $ clk_n $end
$var reg 2 % neg_cnt [1:0] $end
$var reg 2 & pos_cnt [1:0] $end
$upscope $end
$upscope $end
$enddefinitions $end
#0
$dumpvars
b0 &
b1 %
0$
b11 #
0"
0!
$end
#1
b1 &
1"
#2
1!
1$
b10 %
0"
#3
b10 &
1"
#4
b0 %
0"
#5
0!
0$
b0 &
1"
#6
b1 %
0"
#7
b1 &
1"
#8
1!
1$
b10 %
0"
#9
b10 &
1"
#10
b0 %
0"
#11
0!
0$
b0 &
1"
#12
b1 %
0"
#13
b1 &
1"
#14
1!
1$
b10 %
0"
#15
b10 &
1"
#16
b0 %
0"
#17
0!
0$
b0 &
1"
#18
b1 %
0"
#19
b1 &
1"
#20
1!
1$
b10 %
0"
#21
b10 &
1"
#22
b0 %
0"
#23
0!
0$
b0 &
1"
#24
b1 %
0"
#25
b1 &
1"
#26
1!
1$
b10 %
0"
#27
b10 &
1"
#28
b0 %
0"
#29
0!
0$
b0 &
1"
#30
b1 %
0"
#31
b1 &
1"
#32
1!
1$
b10 %
0"
#33
b10 &
1"
#34
b0 %
0"
#35
0!
0$
b0 &
1"
#36
b1 %
0"
#37
b1 &
1"
#38
1!
1$
b10 %
0"
#39
b10 &
1"
#40
b0 %
0"
#41
0!
0$
b0 &
1"
#42
b1 %
0"
#43
b1 &
1"
#44
1!
1$
b10 %
0"
#45
b10 &
1"
#46
b0 %
0"
#47
0!
0$
b0 &
1"
#48
b1 %
0"
#49
b1 &
1"
#50
1!
1$
b10 %
0"
#51
b10 &
1"
#52
b0 %
0"
#53
0!
0$
b0 &
1"
#54
b1 %
0"
#55
b1 &
1"
#56
1!
1$
b10 %
0"
#57
b10 &
1"
#58
b0 %
0"
#59
0!
0$
b0 &
1"
#60
b1 %
0"
#61
b1 &
1"
#62
1!
1$
b10 %
0"
#63
b10 &
1"
#64
b0 %
0"
#65
0!
0$
b0 &
1"
#66
b1 %
0"
#67
b1 &
1"
#68
1!
1$
b10 %
0"
#69
b10 &
1"
#70
b0 %
0"
#71
0!
0$
b0 &
1"
#72
b1 %
0"
#73
b1 &
1"
#74
1!
1$
b10 %
0"
#75
b10 &
1"
#76
b0 %
0"
#77
0!
0$
b0 &
1"
#78
b1 %
0"
#79
b1 &
1"
#80
1!
1$
b10 %
0"
#81
b10 &
1"
#82
b0 %
0"
#83
0!
0$
b0 &
1"
#84
b1 %
0"
#85
b1 &
1"
#86
1!
1$
b10 %
0"
#87
b10 &
1"
#88
b0 %
0"
#89
0!
0$
b0 &
1"
#90
b1 %
0"
#91
b1 &
1"
#92
1!
1$
b10 %
0"
#93
b10 &
1"
#94
b0 %
0"
#95
0!
0$
b0 &
1"
#96
b1 %
0"
#97
b1 &
1"
#98
1!
1$
b10 %
0"
#99
b10 &
1"
#100
b0 %
0"
#101
0!
0$
b0 &
1"
#102
b1 %
0"
#103
b1 &
1"
#104
1!
1$
b10 %
0"
#105
b10 &
1"
#106
b0 %
0"
#107
0!
0$
b0 &
1"
#108
b1 %
0"
#109
b1 &
1"
#110
1!
1$
b10 %
0"
#111
b10 &
1"
#112
b0 %
0"
#113
0!
0$
b0 &
1"
#114
b1 %
0"
#115
b1 &
1"
#116
1!
1$
b10 %
0"
#117
b10 &
1"
#118
b0 %
0"
#119
0!
0$
b0 &
1"
#120
b1 %
0"
#121
b1 &
1"
#122
1!
1$
b10 %
0"
#123
b10 &
1"
#124
b0 %
0"
#125
0!
0$
b0 &
1"
#126
b1 %
0"
#127
b1 &
1"
#128
1!
1$
b10 %
0"
#129
b10 &
1"
#130
b0 %
0"
#131
0!
0$
b0 &
1"
#132
b1 %
0"
#133
b1 &
1"
#134
1!
1$
b10 %
0"
#135
b10 &
1"
#136
b0 %
0"
#137
0!
0$
b0 &
1"
#138
b1 %
0"
#139
b1 &
1"
#140
1!
1$
b10 %
0"
#141
b10 &
1"
#142
b0 %
0"
#143
0!
0$
b0 &
1"
#144
b1 %
0"
#145
b1 &
1"
#146
1!
1$
b10 %
0"
#147
b10 &
1"
#148
b0 %
0"
#149
0!
0$
b0 &
1"
#150
b1 %
0"
#151
b1 &
1"
#152
1!
1$
b10 %
0"
#153
b10 &
1"
#154
b0 %
0"
#155
0!
0$
b0 &
1"
#156
b1 %
0"
#157
b1 &
1"
#158
1!
1$
b10 %
0"
#159
b10 &
1"
#160
b0 %
0"
#161
0!
0$
b0 &
1"
#162
b1 %
0"
#163
b1 &
1"
#164
1!
1$
b10 %
0"
#165
b10 &
1"
#166
b0 %
0"
#167
0!
0$
b0 &
1"
#168
b1 %
0"
#169
b1 &
1"
#170
1!
1$
b10 %
0"
#171
b10 &
1"
#172
b0 %
0"
#173
0!
0$
b0 &
1"
#174
b1 %
0"
#175
b1 &
1"
#176
1!
1$
b10 %
0"
#177
b10 &
1"
#178
b0 %
0"
#179
0!
0$
b0 &
1"
#180
b1 %
0"
#181
b1 &
1"
#182
1!
1$
b10 %
0"
#183
b10 &
1"
#184
b0 %
0"
#185
0!
0$
b0 &
1"
#186
b1 %
0"
#187
b1 &
1"
#188
1!
1$
b10 %
0"
#189
b10 &
1"
#190
b0 %
0"
#191
0!
0$
b0 &
1"
#192
b1 %
0"
#193
b1 &
1"
#194
1!
1$
b10 %
0"
#195
b10 &
1"
#196
b0 %
0"
#197
0!
0$
b0 &
1"
#198
b1 %
0"
#199
b1 &
1"
#200
1!
1$
b10 %
0"
#201
b10 &
1"
#202
b0 %
0"
#203
0!
0$
b0 &
1"
#204
b1 %
0"
#205
b1 &
1"
#206
1!
1$
b10 %
0"
#207
b10 &
1"
#208
b0 %
0"
#209
0!
0$
b0 &
1"
#210
b1 %
0"
#211
b1 &
1"
#212
1!
1$
b10 %
0"
#213
b10 &
1"
#214
b0 %
0"
#215
0!
0$
b0 &
1"
#216
b1 %
0"
#217
b1 &
1"
#218
1!
1$
b10 %
0"
#219
b10 &
1"
#220
b0 %
0"
#221
0!
0$
b0 &
1"
#222
b1 %
0"
#223
b1 &
1"
#224
1!
1$
b10 %
0"
#225
b10 &
1"
#226
b0 %
0"
#227
0!
0$
b0 &
1"
#228
b1 %
0"
#229
b1 &
1"
#230
1!
1$
b10 %
0"
#231
b10 &
1"
#232
b0 %
0"
#233
0!
0$
b0 &
1"
#234
b1 %
0"
#235
b1 &
1"
#236
1!
1$
b10 %
0"
#237
b10 &
1"
#238
b0 %
0"
#239
0!
0$
b0 &
1"
#240
b1 %
0"
#241
b1 &
1"
#242
1!
1$
b10 %
0"
#243
b10 &
1"
#244
b0 %
0"
#245
0!
0$
b0 &
1"
#246
b1 %
0"
#247
b1 &
1"
#248
1!
1$
b10 %
0"
#249
b10 &
1"
#250
b0 %
0"
#251
0!
0$
b0 &
1"
#252
b1 %
0"
#253
b1 &
1"
#254
1!
1$
b10 %
0"
#255
b10 &
1"
#256
b0 %
0"
#257
0!
0$
b0 &
1"
#258
b1 %
0"
#259
b1 &
1"
#260
1!
1$
b10 %
0"
#261
b10 &
1"
#262
b0 %
0"
#263
0!
0$
b0 &
1"
#264
b1 %
0"
#265
b1 &
1"
#266
1!
1$
b10 %
0"
#267
b10 &
1"
#268
b0 %
0"
#269
0!
0$
b0 &
1"
#270
b1 %
0"
#271
b1 &
1"
#272
1!
1$
b10 %
0"
#273
b10 &
1"
#274
b0 %
0"
#275
0!
0$
b0 &
1"
#276
b1 %
0"
#277
b1 &
1"
#278
1!
1$
b10 %
0"
#279
b10 &
1"
#280
b0 %
0"
#281
0!
0$
b0 &
1"
#282
b1 %
0"
#283
b1 &
1"
#284
1!
1$
b10 %
0"
#285
b10 &
1"
#286
b0 %
0"
#287
0!
0$
b0 &
1"
#288
b1 %
0"
#289
b1 &
1"
#290
1!
1$
b10 %
0"
#291
b10 &
1"
#292
b0 %
0"
#293
0!
0$
b0 &
1"
#294
b1 %
0"
#295
b1 &
1"
#296
1!
1$
b10 %
0"
#297
b10 &
1"
#298
b0 %
0"
#299
0!
0$
b0 &
1"
#300
b1 %
0"
#301
b1 &
1"
#302
1!
1$
b10 %
0"
#303
b10 &
1"
#304
b0 %
0"
#305
0!
0$
b0 &
1"
#306
b1 %
0"
#307
b1 &
1"
#308
1!
1$
b10 %
0"
#309
b10 &
1"
#310
b0 %
0"
#311
0!
0$
b0 &
1"
#312
b1 %
0"
#313
b1 &
1"
#314
1!
1$
b10 %
0"
#315
b10 &
1"
#316
b0 %
0"
#317
0!
0$
b0 &
1"
#318
b1 %
0"
#319
b1 &
1"
#320
1!
1$
b10 %
0"
#321
b10 &
1"
#322
b0 %
0"
#323
0!
0$
b0 &
1"
#324
b1 %
0"
#325
b1 &
1"
#326
1!
1$
b10 %
0"
#327
b10 &
1"
#328
b0 %
0"
#329
0!
0$
b0 &
1"
#330
b1 %
0"
#331
b1 &
1"
#332
1!
1$
b10 %
0"
#333
b10 &
1"
#334
b0 %
0"
#335
0!
0$
b0 &
1"
#336
b1 %
0"
#337
b1 &
1"
#338
1!
1$
b10 %
0"
#339
b10 &
1"
#340
b0 %
0"
#341
0!
0$
b0 &
1"
#342
b1 %
0"
#343
b1 &
1"
#344
1!
1$
b10 %
0"
#345
b10 &
1"
#346
b0 %
0"
#347
0!
0$
b0 &
1"
#348
b1 %
0"
#349
b1 &
1"
#350
1!
1$
b10 %
0"
#351
b10 &
1"
#352
b0 %
0"
#353
0!
0$
b0 &
1"
#354
b1 %
0"
#355
b1 &
1"
#356
1!
1$
b10 %
0"
#357
b10 &
1"
#358
b0 %
0"
#359
0!
0$
b0 &
1"
#360
b1 %
0"
#361
b1 &
1"
#362
1!
1$
b10 %
0"
#363
b10 &
1"
#364
b0 %
0"
#365
0!
0$
b0 &
1"
#366
b1 %
0"
#367
b1 &
1"
#368
1!
1$
b10 %
0"
#369
b10 &
1"
#370
b0 %
0"
#371
0!
0$
b0 &
1"
#372
b1 %
0"
#373
b1 &
1"
#374
1!
1$
b10 %
0"
#375
b10 &
1"
#376
b0 %
0"
#377
0!
0$
b0 &
1"
#378
b1 %
0"
#379
b1 &
1"
#380
1!
1$
b10 %
0"
#381
b10 &
1"
#382
b0 %
0"
#383
0!
0$
b0 &
1"
#384
b1 %
0"
#385
b1 &
1"
#386
1!
1$
b10 %
0"
#387
b10 &
1"
#388
b0 %
0"
#389
0!
0$
b0 &
1"
#390
b1 %
0"
#391
b1 &
1"
#392
1!
1$
b10 %
0"
#393
b10 &
1"
#394
b0 %
0"
#395
0!
0$
b0 &
1"
#396
b1 %
0"
#397
b1 &
1"
#398
1!
1$
b10 %
0"
#399
b10 &
1"
#400
b0 %
0"
#401
0!
0$
b0 &
1"
#402
b1 %
0"
#403
b1 &
1"
#404
1!
1$
b10 %
0"
#405
b10 &
1"
#406
b0 %
0"
#407
0!
0$
b0 &
1"
#408
b1 %
0"
#409
b1 &
1"
#410
1!
1$
b10 %
0"
#411
b10 &
1"
#412
b0 %
0"
#413
0!
0$
b0 &
1"
#414
b1 %
0"
#415
b1 &
1"
#416
1!
1$
b10 %
0"
#417
b10 &
1"
#418
b0 %
0"
#419
0!
0$
b0 &
1"
#420
b1 %
0"
#421
b1 &
1"
#422
1!
1$
b10 %
0"
#423
b10 &
1"
#424
b0 %
0"
#425
0!
0$
b0 &
1"
#426
b1 %
0"
#427
b1 &
1"
#428
1!
1$
b10 %
0"
#429
b10 &
1"
#430
b0 %
0"
#431
0!
0$
b0 &
1"
#432
b1 %
0"
#433
b1 &
1"
#434
1!
1$
b10 %
0"
#435
b10 &
1"
#436
b0 %
0"
#437
0!
0$
b0 &
1"
#438
b1 %
0"
#439
b1 &
1"
#440
1!
1$
b10 %
0"
#441
b10 &
1"
#442
b0 %
0"
#443
0!
0$
b0 &
1"
#444
b1 %
0"
#445
b1 &
1"
#446
1!
1$
b10 %
0"
#447
b10 &
1"
#448
b0 %
0"
#449
0!
0$
b0 &
1"
#450
b1 %
0"
#451
b1 &
1"
#452
1!
1$
b10 %
0"
#453
b10 &
1"
#454
b0 %
0"
#455
0!
0$
b0 &
1"
#456
b1 %
0"
#457
b1 &
1"
#458
1!
1$
b10 %
0"
#459
b10 &
1"
#460
b0 %
0"
#461
0!
0$
b0 &
1"
#462
b1 %
0"
#463
b1 &
1"
#464
1!
1$
b10 %
0"
#465
b10 &
1"
#466
b0 %
0"
#467
0!
0$
b0 &
1"
#468
b1 %
0"
#469
b1 &
1"
#470
1!
1$
b10 %
0"
#471
b10 &
1"
#472
b0 %
0"
#473
0!
0$
b0 &
1"
#474
b1 %
0"
#475
b1 &
1"
#476
1!
1$
b10 %
0"
#477
b10 &
1"
#478
b0 %
0"
#479
0!
0$
b0 &
1"
#480
b1 %
0"
#481
b1 &
1"
#482
1!
1$
b10 %
0"
#483
b10 &
1"
#484
b0 %
0"
#485
0!
0$
b0 &
1"
#486
b1 %
0"
#487
b1 &
1"
#488
1!
1$
b10 %
0"
#489
b10 &
1"
#490
b0 %
0"
#491
0!
0$
b0 &
1"
#492
b1 %
0"
#493
b1 &
1"
#494
1!
1$
b10 %
0"
#495
b10 &
1"
#496
b0 %
0"
#497
0!
0$
b0 &
1"
#498
b1 %
0"
#499
b1 &
1"
#500
1!
1$
b10 %
0"
#501
b10 &
1"
#502
b0 %
0"
#503
0!
0$
b0 &
1"
#504
b1 %
0"
#505
b1 &
1"
#506
1!
1$
b10 %
0"
#507
b10 &
1"
#508
b0 %
0"
#509
0!
0$
b0 &
1"
#510
b1 %
0"
#511
b1 &
1"
#512
1!
1$
b10 %
0"
#513
b10 &
1"
#514
b0 %
0"
#515
0!
0$
b0 &
1"
#516
b1 %
0"
#517
b1 &
1"
#518
1!
1$
b10 %
0"
#519
b10 &
1"
#520
b0 %
0"
#521
0!
0$
b0 &
1"
#522
b1 %
0"
#523
b1 &
1"
#524
1!
1$
b10 %
0"
#525
b10 &
1"
#526
b0 %
0"
#527
0!
0$
b0 &
1"
#528
b1 %
0"
#529
b1 &
1"
#530
1!
1$
b10 %
0"
#531
b10 &
1"
#532
b0 %
0"
#533
0!
0$
b0 &
1"
#534
b1 %
0"
#535
b1 &
1"
#536
1!
1$
b10 %
0"
#537
b10 &
1"
#538
b0 %
0"
#539
0!
0$
b0 &
1"
#540
b1 %
0"
#541
b1 &
1"
#542
1!
1$
b10 %
0"
#543
b10 &
1"
#544
b0 %
0"
#545
0!
0$
b0 &
1"
#546
b1 %
0"
#547
b1 &
1"
#548
1!
1$
b10 %
0"
#549
b10 &
1"
#550
b0 %
0"
#551
0!
0$
b0 &
1"
#552
b1 %
0"
#553
b1 &
1"
#554
1!
1$
b10 %
0"
#555
b10 &
1"
#556
b0 %
0"
#557
0!
0$
b0 &
1"
#558
b1 %
0"
#559
b1 &
1"
#560
1!
1$
b10 %
0"
#561
b10 &
1"
#562
b0 %
0"
#563
0!
0$
b0 &
1"
#564
b1 %
0"
#565
b1 &
1"
#566
1!
1$
b10 %
0"
#567
b10 &
1"
#568
b0 %
0"
#569
0!
0$
b0 &
1"
#570
b1 %
0"
#571
b1 &
1"
#572
1!
1$
b10 %
0"
#573
b10 &
1"
#574
b0 %
0"
#575
0!
0$
b0 &
1"
#576
b1 %
0"
#577
b1 &
1"
#578
1!
1$
b10 %
0"
#579
b10 &
1"
#580
b0 %
0"
#581
0!
0$
b0 &
1"
#582
b1 %
0"
#583
b1 &
1"
#584
1!
1$
b10 %
0"
#585
b10 &
1"
#586
b0 %
0"
#587
0!
0$
b0 &
1"
#588
b1 %
0"
#589
b1 &
1"
#590
1!
1$
b10 %
0"
#591
b10 &
1"
#592
b0 %
0"
#593
0!
0$
b0 &
1"
#594
b1 %
0"
#595
b1 &
1"
#596
1!
1$
b10 %
0"
#597
b10 &
1"
#598
b0 %
0"
#599
0!
0$
b0 &
1"
#600
b1 %
0"
#601
b1 &
1"
#602
1!
1$
b10 %
0"
#603
b10 &
1"
#604
b0 %
0"
#605
0!
0$
b0 &
1"
#606
b1 %
0"
#607
b1 &
1"
#608
1!
1$
b10 %
0"
#609
b10 &
1"
#610
b0 %
0"
#611
0!
0$
b0 &
1"
#612
b1 %
0"
#613
b1 &
1"
#614
1!
1$
b10 %
0"
#615
b10 &
1"
#616
b0 %
0"
#617
0!
0$
b0 &
1"
#618
b1 %
0"
#619
b1 &
1"
#620
1!
1$
b10 %
0"
#621
b10 &
1"
#622
b0 %
0"
#623
0!
0$
b0 &
1"
#624
b1 %
0"
#625
b1 &
1"
#626
1!
1$
b10 %
0"
#627
b10 &
1"
#628
b0 %
0"
#629
0!
0$
b0 &
1"
#630
b1 %
0"
#631
b1 &
1"
#632
1!
1$
b10 %
0"
#633
b10 &
1"
#634
b0 %
0"
#635
0!
0$
b0 &
1"
#636
b1 %
0"
#637
b1 &
1"
#638
1!
1$
b10 %
0"
#639
b10 &
1"
#640
b0 %
0"
#641
0!
0$
b0 &
1"
#642
b1 %
0"
#643
b1 &
1"
#644
1!
1$
b10 %
0"
#645
b10 &
1"
#646
b0 %
0"
#647
0!
0$
b0 &
1"
#648
b1 %
0"
#649
b1 &
1"
#650
1!
1$
b10 %
0"
#651
b10 &
1"
#652
b0 %
0"
#653
0!
0$
b0 &
1"
#654
b1 %
0"
#655
b1 &
1"
#656
1!
1$
b10 %
0"
#657
b10 &
1"
#658
b0 %
0"
#659
0!
0$
b0 &
1"
#660
b1 %
0"
#661
b1 &
1"
#662
1!
1$
b10 %
0"
#663
b10 &
1"
#664
b0 %
0"
#665
0!
0$
b0 &
1"
#666
b1 %
0"
#667
b1 &
1"
#668
1!
1$
b10 %
0"
#669
b10 &
1"
#670
b0 %
0"
#671
0!
0$
b0 &
1"
#672
b1 %
0"
#673
b1 &
1"
#674
1!
1$
b10 %
0"
#675
b10 &
1"
#676
b0 %
0"
#677
0!
0$
b0 &
1"
#678
b1 %
0"
#679
b1 &
1"
#680
1!
1$
b10 %
0"
#681
b10 &
1"
#682
b0 %
0"
#683
0!
0$
b0 &
1"
#684
b1 %
0"
#685
b1 &
1"
#686
1!
1$
b10 %
0"
#687
b10 &
1"
#688
b0 %
0"
#689
0!
0$
b0 &
1"
#690
b1 %
0"
#691
b1 &
1"
#692
1!
1$
b10 %
0"
#693
b10 &
1"
#694
b0 %
0"
#695
0!
0$
b0 &
1"
#696
b1 %
0"
#697
b1 &
1"
#698
1!
1$
b10 %
0"
#699
b10 &
1"
#700
b0 %
0"
#701
0!
0$
b0 &
1"
#702
b1 %
0"
#703
b1 &
1"
#704
1!
1$
b10 %
0"
#705
b10 &
1"
#706
b0 %
0"
#707
0!
0$
b0 &
1"
#708
b1 %
0"
#709
b1 &
1"
#710
1!
1$
b10 %
0"
#711
b10 &
1"
#712
b0 %
0"
#713
0!
0$
b0 &
1"
#714
b1 %
0"
#715
b1 &
1"
#716
1!
1$
b10 %
0"
#717
b10 &
1"
#718
b0 %
0"
#719
0!
0$
b0 &
1"
#720
b1 %
0"
#721
b1 &
1"
#722
1!
1$
b10 %
0"
#723
b10 &
1"
#724
b0 %
0"
#725
0!
0$
b0 &
1"
#726
b1 %
0"
#727
b1 &
1"
#728
1!
1$
b10 %
0"
#729
b10 &
1"
#730
b0 %
0"
#731
0!
0$
b0 &
1"
#732
b1 %
0"
#733
b1 &
1"
#734
1!
1$
b10 %
0"
#735
b10 &
1"
#736
b0 %
0"
#737
0!
0$
b0 &
1"
#738
b1 %
0"
#739
b1 &
1"
#740
1!
1$
b10 %
0"
#741
b10 &
1"
#742
b0 %
0"
#743
0!
0$
b0 &
1"
#744
b1 %
0"
#745
b1 &
1"
#746
1!
1$
b10 %
0"
#747
b10 &
1"
#748
b0 %
0"
#749
0!
0$
b0 &
1"
#750
b1 %
0"
#751
b1 &
1"
#752
1!
1$
b10 %
0"
#753
b10 &
1"
#754
b0 %
0"
#755
0!
0$
b0 &
1"
#756
b1 %
0"
#757
b1 &
1"
#758
1!
1$
b10 %
0"
#759
b10 &
1"
#760
b0 %
0"
#761
0!
0$
b0 &
1"
#762
b1 %
0"
#763
b1 &
1"
#764
1!
1$
b10 %
0"
#765
b10 &
1"
#766
b0 %
0"
#767
0!
0$
b0 &
1"
#768
b1 %
0"
#769
b1 &
1"
#770
1!
1$
b10 %
0"
#771
b10 &
1"
#772
b0 %
0"
#773
0!
0$
b0 &
1"
#774
b1 %
0"
#775
b1 &
1"
#776
1!
1$
b10 %
0"
#777
b10 &
1"
#778
b0 %
0"
#779
0!
0$
b0 &
1"
#780
b1 %
0"
#781
b1 &
1"
#782
1!
1$
b10 %
0"
#783
b10 &
1"
#784
b0 %
0"
#785
0!
0$
b0 &
1"
#786
b1 %
0"
#787
b1 &
1"
#788
1!
1$
b10 %
0"
#789
b10 &
1"
#790
b0 %
0"
#791
0!
0$
b0 &
1"
#792
b1 %
0"
#793
b1 &
1"
#794
1!
1$
b10 %
0"
#795
b10 &
1"
#796
b0 %
0"
#797
0!
0$
b0 &
1"
#798
b1 %
0"
#799
b1 &
1"
#800
1!
1$
b10 %
0"
#801
b10 &
1"
#802
b0 %
0"
#803
0!
0$
b0 &
1"
#804
b1 %
0"
#805
b1 &
1"
#806
1!
1$
b10 %
0"
#807
b10 &
1"
#808
b0 %
0"
#809
0!
0$
b0 &
1"
#810
b1 %
0"
#811
b1 &
1"
#812
1!
1$
b10 %
0"
#813
b10 &
1"
#814
b0 %
0"
#815
0!
0$
b0 &
1"
#816
b1 %
0"
#817
b1 &
1"
#818
1!
1$
b10 %
0"
#819
b10 &
1"
#820
b0 %
0"
#821
0!
0$
b0 &
1"
#822
b1 %
0"
#823
b1 &
1"
#824
1!
1$
b10 %
0"
#825
b10 &
1"
#826
b0 %
0"
#827
0!
0$
b0 &
1"
#828
b1 %
0"
#829
b1 &
1"
#830
1!
1$
b10 %
0"
#831
b10 &
1"
#832
b0 %
0"
#833
0!
0$
b0 &
1"
#834
b1 %
0"
#835
b1 &
1"
#836
1!
1$
b10 %
0"
#837
b10 &
1"
#838
b0 %
0"
#839
0!
0$
b0 &
1"
#840
b1 %
0"
#841
b1 &
1"
#842
1!
1$
b10 %
0"
#843
b10 &
1"
#844
b0 %
0"
#845
0!
0$
b0 &
1"
#846
b1 %
0"
#847
b1 &
1"
#848
1!
1$
b10 %
0"
#849
b10 &
1"
#850
b0 %
0"
#851
0!
0$
b0 &
1"
#852
b1 %
0"
#853
b1 &
1"
#854
1!
1$
b10 %
0"
#855
b10 &
1"
#856
b0 %
0"
#857
0!
0$
b0 &
1"
#858
b1 %
0"
#859
b1 &
1"
#860
1!
1$
b10 %
0"
#861
b10 &
1"
#862
b0 %
0"
#863
0!
0$
b0 &
1"
#864
b1 %
0"
#865
b1 &
1"
#866
1!
1$
b10 %
0"
#867
b10 &
1"
#868
b0 %
0"
#869
0!
0$
b0 &
1"
#870
b1 %
0"
#871
b1 &
1"
#872
1!
1$
b10 %
0"
#873
b10 &
1"
#874
b0 %
0"
#875
0!
0$
b0 &
1"
#876
b1 %
0"
#877
b1 &
1"
#878
1!
1$
b10 %
0"
#879
b10 &
1"
#880
b0 %
0"
#881
0!
0$
b0 &
1"
#882
b1 %
0"
#883
b1 &
1"
#884
1!
1$
b10 %
0"
#885
b10 &
1"
#886
b0 %
0"
#887
0!
0$
b0 &
1"
#888
b1 %
0"
#889
b1 &
1"
#890
1!
1$
b10 %
0"
#891
b10 &
1"
#892
b0 %
0"
#893
0!
0$
b0 &
1"
#894
b1 %
0"
#895
b1 &
1"
#896
1!
1$
b10 %
0"
#897
b10 &
1"
#898
b0 %
0"
#899
0!
0$
b0 &
1"
#900
b1 %
0"
#901
b1 &
1"
#902
1!
1$
b10 %
0"
#903
b10 &
1"
#904
b0 %
0"
#905
0!
0$
b0 &
1"
#906
b1 %
0"
#907
b1 &
1"
#908
1!
1$
b10 %
0"
#909
b10 &
1"
#910
b0 %
0"
#911
0!
0$
b0 &
1"
#912
b1 %
0"
#913
b1 &
1"
#914
1!
1$
b10 %
0"
#915
b10 &
1"
#916
b0 %
0"
#917
0!
0$
b0 &
1"
#918
b1 %
0"
#919
b1 &
1"
#920
1!
1$
b10 %
0"
#921
b10 &
1"
#922
b0 %
0"
#923
0!
0$
b0 &
1"
#924
b1 %
0"
#925
b1 &
1"
#926
1!
1$
b10 %
0"
#927
b10 &
1"
#928
b0 %
0"
#929
0!
0$
b0 &
1"
#930
b1 %
0"
#931
b1 &
1"
#932
1!
1$
b10 %
0"
#933
b10 &
1"
#934
b0 %
0"
#935
0!
0$
b0 &
1"
#936
b1 %
0"
#937
b1 &
1"
#938
1!
1$
b10 %
0"
#939
b10 &
1"
#940
b0 %
0"
#941
0!
0$
b0 &
1"
#942
b1 %
0"
#943
b1 &
1"
#944
1!
1$
b10 %
0"
#945
b10 &
1"
#946
b0 %
0"
#947
0!
0$
b0 &
1"
#948
b1 %
0"
#949
b1 &
1"
#950
1!
1$
b10 %
0"
#951
b10 &
1"
#952
b0 %
0"
#953
0!
0$
b0 &
1"
#954
b1 %
0"
#955
b1 &
1"
#956
1!
1$
b10 %
0"
#957
b10 &
1"
#958
b0 %
0"
#959
0!
0$
b0 &
1"
#960
b1 %
0"
#961
b1 &
1"
#962
1!
1$
b10 %
0"
#963
b10 &
1"
#964
b0 %
0"
#965
0!
0$
b0 &
1"
#966
b1 %
0"
#967
b1 &
1"
#968
1!
1$
b10 %
0"
#969
b10 &
1"
#970
b0 %
0"
#971
0!
0$
b0 &
1"
#972
b1 %
0"
#973
b1 &
1"
#974
1!
1$
b10 %
0"
#975
b10 &
1"
#976
b0 %
0"
#977
0!
0$
b0 &
1"
#978
b1 %
0"
#979
b1 &
1"
#980
1!
1$
b10 %
0"
#981
b10 &
1"
#982
b0 %
0"
#983
0!
0$
b0 &
1"
#984
b1 %
0"
#985
b1 &
1"
#986
1!
1$
b10 %
0"
#987
b10 &
1"
#988
b0 %
0"
#989
0!
0$
b0 &
1"
#990
b1 %
0"
#991
b1 &
1"
#992
1!
1$
b10 %
0"
#993
b10 &
1"
#994
b0 %
0"
#995
0!
0$
b0 &
1"
#996
b1 %
0"
#997
b1 &
1"
#998
1!
1$
b10 %
0"
#999
b10 &
1"
#1000
b0 %
0"
#1001
0!
0$
b0 &
1"
#1002
b1 %
0"
#1003
b1 &
1"
#1004
1!
1$
b10 %
0"
#1005
b10 &
1"
#1006
b0 %
0"
#1007
0!
0$
b0 &
1"
#1008
b1 %
0"
#1009
b1 &
1"
#1010
1!
1$
b10 %
0"
#1011
b10 &
1"
#1012
b0 %
0"
#1013
0!
0$
b0 &
1"
#1014
b1 %
0"
#1015
b1 &
1"
#1016
1!
1$
b10 %
0"
#1017
b10 &
1"
#1018
b0 %
0"
#1019
0!
0$
b0 &
1"
#1020
b1 %
0"
#1021
b1 &
1"
#1022
1!
1$
b10 %
0"
#1023
b10 &
1"
#1024
b0 %
0"
#1025
0!
0$
b0 &
1"
#1026
b1 %
0"
#1027
b1 &
1"
#1028
1!
1$
b10 %
0"
#1029
b10 &
1"
#1030
b0 %
0"
#1031
0!
0$
b0 &
1"
#1032
b1 %
0"
#1033
b1 &
1"
#1034
1!
1$
b10 %
0"
#1035
b10 &
1"
#1036
b0 %
0"
#1037
0!
0$
b0 &
1"
#1038
b1 %
0"
#1039
b1 &
1"
#1040
1!
1$
b10 %
0"
#1041
b10 &
1"
#1042
b0 %
0"
#1043
0!
0$
b0 &
1"
#1044
b1 %
0"
#1045
b1 &
1"
#1046
1!
1$
b10 %
0"
#1047
b10 &
1"
#1048
b0 %
0"
#1049
0!
0$
b0 &
1"
#1050
b1 %
0"
#1051
b1 &
1"
#1052
1!
1$
b10 %
0"
#1053
b10 &
1"
#1054
b0 %
0"
#1055
0!
0$
b0 &
1"
#1056
b1 %
0"
#1057
b1 &
1"
#1058
1!
1$
b10 %
0"
#1059
b10 &
1"
#1060
b0 %
0"
