benches/i2s_tx/frqdivmod.v
module frqdivmod(clk, s_out);
parameter DIV=2;
// calculated parameters
parameter WITH = ($clog2(DIV+1)>0) ? $clog2(DIV+1) : 1;

input wire clk;
output wire s_out;

reg clk_n; 

reg [(WITH-1):0] pos_cnt; 
reg [(WITH-1):0] neg_cnt; 

wire [(WITH-1):0] div_value = DIV[(WITH-1):0];

//div2 - 0  -- 1
//div4 - 1     2
//div6 - 2     3
//div8 - 3     4
initial begin
	clk_n <= 1'b0;
	pos_cnt <= {(WITH){1'b0}} + (DIV/2 - 1);
	neg_cnt <= {(WITH){1'b0}};
end

assign s_out = (DIV==1) ? clk : clk_n;

always @ (posedge clk) begin
	pos_cnt <= (pos_cnt + 1'b1) % div_value;
end

always @ (negedge clk) begin
	neg_cnt <= (neg_cnt + 1'b1) % div_value;
end

always @(clk, pos_cnt, neg_cnt) begin //pos_cnt in sens list addd for resolve warning "variable is read inside the Always Construct but isn't in the Always Construct's Event Control"
	if ((DIV%2) == 1'b0) begin
		clk_n <= ( pos_cnt >= (DIV/2)) ? 1'b1 : 1'b0;
	end else begin
		clk_n <= (( pos_cnt > (DIV/2)) || ( neg_cnt > (DIV/2))) ? 1'b1 : 1'b0;
	end
end
	
endmodule

benches/frqdivmod/testbench.v
module testbench();

reg tb_clk;

wire out_val;
frqdivmod #(.DIV(3)) div1(tb_clk, out_val);

initial
begin
    $dumpfile("bench.vcd");
    $dumpvars(0,testbench);

    $display("starting testbench!!!!");
	$display("bits for 0..9", $clog2(1));
	
	tb_clk <= 0;
	repeat (20000) begin
		#1;
		tb_clk <= 1;
		#1;
		tb_clk <= 0;
	end
	
    $display("finished OK!");
    $finish;
end
	
endmodule

benches/frqdivmod/bench.vcd
$date
	Mon Sep 07 21:18:46 2015
$end
$version
	Icarus Verilog
$end
$timescale
	1s
$end
$scope module testbench $end
$var wire 1 ! out_val $end
$var reg 1 " tb_clk $end
$scope module div1 $end
$var wire 1 " clk $end
$var wire 1 ! s_out $end
$var reg 1 # clk_n $end
$var reg 24 $ neg_cnt [23:0] $end
$var reg 24 % pos_cnt [23:0] $end
$upscope $end
$upscope $end
$enddefinitions $end
#0
$dumpvars
b0 %
b1 $
0#
0"
0!
$end
#1
b1 %
1"
#2
b10 $
0"
#3
b10 %
1"
#4
b11 $
0"
#5
b11 %
1"
#6
b100 $
0"
#7
b100 %
1"
#8
b101 $
0"
#9
b101 %
1"
#10
b110 $
0"
#11
b110 %
1"
#12
b111 $
0"
#13
b111 %
1"
#14
b1000 $
0"
#15
b1000 %
1"
#16
b1001 $
0"
#17
b1001 %
1"
#18
b1010 $
0"
#19
b1010 %
1"
#20
b1011 $
0"
#21
b1011 %
1"
#22
b1100 $
0"
#23
b1100 %
1"
#24
b1101 $
0"
#25
b1101 %
1"
#26
b1110 $
0"
#27
b1110 %
1"
#28
b1111 $
0"
#29
b1111 %
1"
#30
b10000 $
0"
#31
b10000 %
1"
#32
b10001 $
0"
#33
b10001 %
1"
#34
b10010 $
0"
#35
b10010 %
1"
#36
b10011 $
0"
#37
b10011 %
1"
#38
b10100 $
0"
#39
b10100 %
1"
#40
b10101 $
0"
#41
b10101 %
1"
#42
b10110 $
0"
#43
b10110 %
1"
#44
b10111 $
0"
#45
b10111 %
1"
#46
b11000 $
0"
#47
b11000 %
1"
#48
b11001 $
0"
#49
b11001 %
1"
#50
b11010 $
0"
#51
b11010 %
1"
#52
b11011 $
0"
#53
b11011 %
1"
#54
b11100 $
0"
#55
b11100 %
1"
#56
b11101 $
0"
#57
b11101 %
1"
#58
b11110 $
0"
#59
b11110 %
1"
#60
b11111 $
0"
#61
b11111 %
1"
#62
b100000 $
0"
#63
b100000 %
1"
#64
b100001 $
0"
#65
b100001 %
1"
#66
b100010 $
0"
#67
b100010 %
1"
#68
b100011 $
0"
#69
b100011 %
1"
#70
b100100 $
0"
#71
b100100 %
1"
#72
b100101 $
0"
#73
b100101 %
1"
#74
b100110 $
0"
#75
b100110 %
1"
#76
b100111 $
0"
#77
b100111 %
1"
#78
b101000 $
0"
#79
b101000 %
1"
#80
b101001 $
0"
#81
b101001 %
1"
#82
b101010 $
0"
#83
b101010 %
1"
#84
b101011 $
0"
#85
b101011 %
1"
#86
b101100 $
0"
#87
b101100 %
1"
#88
b101101 $
0"
#89
b101101 %
1"
#90
b101110 $
0"
#91
b101110 %
1"
#92
b101111 $
0"
#93
b101111 %
1"
#94
b110000 $
0"
#95
b110000 %
1"
#96
b110001 $
0"
#97
b110001 %
1"
#98
b110010 $
0"
#99
b110010 %
1"
#100
b110011 $
0"
#101
b110011 %
1"
#102
b110100 $
0"
#103
b110100 %
1"
#104
b110101 $
0"
#105
b110101 %
1"
#106
b110110 $
0"
#107
b110110 %
1"
#108
b110111 $
0"
#109
b110111 %
1"
#110
b111000 $
0"
#111
b111000 %
1"
#112
b111001 $
0"
#113
b111001 %
1"
#114
b111010 $
0"
#115
b111010 %
1"
#116
b111011 $
0"
#117
b111011 %
1"
#118
b111100 $
0"
#119
b111100 %
1"
#120
b111101 $
0"
#121
b111101 %
1"
#122
b111110 $
0"
#123
b111110 %
1"
#124
b111111 $
0"
#125
b111111 %
1"
#126
b1000000 $
0"
#127
b1000000 %
1"
#128
b1000001 $
0"
#129
b1000001 %
1"
#130
b1000010 $
0"
#131
b1000010 %
1"
#132
b1000011 $
0"
#133
b1000011 %
1"
#134
b1000100 $
0"
#135
b1000100 %
1"
#136
b1000101 $
0"
#137
b1000101 %
1"
#138
b1000110 $
0"
#139
b1000110 %
1"
#140
b1000111 $
0"
#141
b1000111 %
1"
#142
b1001000 $
0"
#143
b1001000 %
1"
#144
b1001001 $
0"
#145
b1001001 %
1"
#146
b1001010 $
0"
#147
b1001010 %
1"
#148
b1001011 $
0"
#149
b1001011 %
1"
#150
b1001100 $
0"
#151
b1001100 %
1"
#152
b1001101 $
0"
#153
b1001101 %
1"
#154
b1001110 $
0"
#155
b1001110 %
1"
#156
b1001111 $
0"
#157
b1001111 %
1"
#158
b1010000 $
0"
#159
b1010000 %
1"
#160
b1010001 $
0"
#161
b1010001 %
1"
#162
b1010010 $
0"
#163
b1010010 %
1"
#164
b1010011 $
0"
#165
b1010011 %
1"
#166
b1010100 $
0"
#167
b1010100 %
1"
#168
b1010101 $
0"
#169
b1010101 %
1"
#170
b1010110 $
0"
#171
b1010110 %
1"
#172
b1010111 $
0"
#173
b1010111 %
1"
#174
b1011000 $
0"
#175
b1011000 %
1"
#176
b1011001 $
0"
#177
b1011001 %
1"
#178
b1011010 $
0"
#179
b1011010 %
1"
#180
b1011011 $
0"
#181
b1011011 %
1"
#182
b1011100 $
0"
#183
b1011100 %
1"
#184
b1011101 $
0"
#185
b1011101 %
1"
#186
b1011110 $
0"
#187
b1011110 %
1"
#188
b1011111 $
0"
#189
b1011111 %
1"
#190
b1100000 $
0"
#191
b1100000 %
1"
#192
b1100001 $
0"
#193
b1100001 %
1"
#194
b1100010 $
0"
#195
b1100010 %
1"
#196
b1100011 $
0"
#197
b1100011 %
1"
#198
b1100100 $
0"
#199
b1100100 %
1"
#200
b1100101 $
0"
#201
b1100101 %
1"
#202
b1100110 $
0"
#203
b1100110 %
1"
#204
b1100111 $
0"
#205
b1100111 %
1"
#206
b1101000 $
0"
#207
b1101000 %
1"
#208
b1101001 $
0"
#209
b1101001 %
1"
#210
b1101010 $
0"
#211
b1101010 %
1"
#212
b1101011 $
0"
#213
b1101011 %
1"
#214
b1101100 $
0"
#215
b1101100 %
1"
#216
b1101101 $
0"
#217
b1101101 %
1"
#218
b1101110 $
0"
#219
b1101110 %
1"
#220
b1101111 $
0"
#221
b1101111 %
1"
#222
b1110000 $
0"
#223
b1110000 %
1"
#224
b1110001 $
0"
#225
b1110001 %
1"
#226
b1110010 $
0"
#227
b1110010 %
1"
#228
b1110011 $
0"
#229
b1110011 %
1"
#230
b1110100 $
0"
#231
b1110100 %
1"
#232
b1110101 $
0"
#233
b1110101 %
1"
#234
b1110110 $
0"
#235
b1110110 %
1"
#236
b1110111 $
0"
#237
b1110111 %
1"
#238
b1111000 $
0"
#239
b1111000 %
1"
#240
b1111001 $
0"
#241
b1111001 %
1"
#242
b1111010 $
0"
#243
b1111010 %
1"
#244
b1111011 $
0"
#245
b1111011 %
1"
#246
b1111100 $
0"
#247
b1111100 %
1"
#248
b1111101 $
0"
#249
b1111101 %
1"
#250
b1111110 $
0"
#251
b1111110 %
1"
#252
b1111111 $
0"
#253
b1111111 %
1"
#254
b10000000 $
0"
#255
b10000000 %
1"
#256
b10000001 $
0"
#257
b10000001 %
1"
#258
b10000010 $
0"
#259
b10000010 %
1"
#260
b10000011 $
0"
#261
b10000011 %
1"
#262
b10000100 $
0"
#263
b10000100 %
1"
#264
b10000101 $
0"
#265
b10000101 %
1"
#266
b10000110 $
0"
#267
b10000110 %
1"
#268
b10000111 $
0"
#269
b10000111 %
1"
#270
b10001000 $
0"
#271
b10001000 %
1"
#272
b10001001 $
0"
#273
b10001001 %
1"
#274
b10001010 $
0"
#275
b10001010 %
1"
#276
b10001011 $
0"
#277
b10001011 %
1"
#278
b10001100 $
0"
#279
b10001100 %
1"
#280
b10001101 $
0"
#281
b10001101 %
1"
#282
b10001110 $
0"
#283
b10001110 %
1"
#284
b10001111 $
0"
#285
b10001111 %
1"
#286
b10010000 $
0"
#287
b10010000 %
1"
#288
b10010001 $
0"
#289
b10010001 %
1"
#290
b10010010 $
0"
#291
b10010010 %
1"
#292
b10010011 $
0"
#293
b10010011 %
1"
#294
b10010100 $
0"
#295
b10010100 %
1"
#296
b10010101 $
0"
#297
b10010101 %
1"
#298
b10010110 $
0"
#299
b10010110 %
1"
#300
b10010111 $
0"
#301
b10010111 %
1"
#302
b10011000 $
0"
#303
b10011000 %
1"
#304
b10011001 $
0"
#305
b10011001 %
1"
#306
b10011010 $
0"
#307
b10011010 %
1"
#308
b10011011 $
0"
#309
b10011011 %
1"
#310
b10011100 $
0"
#311
b10011100 %
1"
#312
b10011101 $
0"
#313
b10011101 %
1"
#314
b10011110 $
0"
#315
b10011110 %
1"
#316
b10011111 $
0"
#317
b10011111 %
1"
#318
b10100000 $
0"
#319
b10100000 %
1"
#320
b10100001 $
0"
#321
b10100001 %
1"
#322
b10100010 $
0"
#323
b10100010 %
1"
#324
b10100011 $
0"
#325
b10100011 %
1"
#326
b10100100 $
0"
#327
b10100100 %
1"
#328
b10100101 $
0"
#329
b10100101 %
1"
#330
b10100110 $
0"
#331
b10100110 %
1"
#332
b10100111 $
0"
#333
b10100111 %
1"
#334
b10101000 $
0"
#335
b10101000 %
1"
#336
b10101001 $
0"
#337
b10101001 %
1"
#338
b10101010 $
0"
#339
b10101010 %
1"
#340
b10101011 $
0"
#341
b10101011 %
1"
#342
b10101100 $
0"
#343
b10101100 %
1"
#344
b10101101 $
0"
#345
b10101101 %
1"
#346
b10101110 $
0"
#347
b10101110 %
1"
#348
b10101111 $
0"
#349
b10101111 %
1"
#350
b10110000 $
0"
#351
b10110000 %
1"
#352
b10110001 $
0"
#353
b10110001 %
1"
#354
b10110010 $
0"
#355
b10110010 %
1"
#356
b10110011 $
0"
#357
b10110011 %
1"
#358
b10110100 $
0"
#359
b10110100 %
1"
#360
b10110101 $
0"
#361
b10110101 %
1"
#362
b10110110 $
0"
#363
b10110110 %
1"
#364
b10110111 $
0"
#365
b10110111 %
1"
#366
b10111000 $
0"
#367
b10111000 %
1"
#368
b10111001 $
0"
#369
b10111001 %
1"
#370
b10111010 $
0"
#371
b10111010 %
1"
#372
b10111011 $
0"
#373
b10111011 %
1"
#374
b10111100 $
0"
#375
b10111100 %
1"
#376
b10111101 $
0"
#377
b10111101 %
1"
#378
b10111110 $
0"
#379
b10111110 %
1"
#380
b10111111 $
0"
#381
b10111111 %
1"
#382
b11000000 $
0"
#383
b11000000 %
1"
#384
b11000001 $
0"
#385
b11000001 %
1"
#386
b11000010 $
0"
#387
b11000010 %
1"
#388
b11000011 $
0"
#389
b11000011 %
1"
#390
b11000100 $
0"
#391
b11000100 %
1"
#392
b11000101 $
0"
#393
b11000101 %
1"
#394
b11000110 $
0"
#395
b11000110 %
1"
#396
b11000111 $
0"
#397
b11000111 %
1"
#398
b11001000 $
0"
#399
b11001000 %
1"
#400
b11001001 $
0"
#401
b11001001 %
1"
#402
b11001010 $
0"
#403
b11001010 %
1"
#404
b11001011 $
0"
#405
b11001011 %
1"
#406
b11001100 $
0"
#407
b11001100 %
1"
#408
b11001101 $
0"
#409
b11001101 %
1"
#410
b11001110 $
0"
#411
b11001110 %
1"
#412
b11001111 $
0"
#413
b11001111 %
1"
#414
b11010000 $
0"
#415
b11010000 %
1"
#416
b11010001 $
0"
#417
b11010001 %
1"
#418
b11010010 $
0"
#419
b11010010 %
1"
#420
b11010011 $
0"
#421
b11010011 %
1"
#422
b11010100 $
0"
#423
b11010100 %
1"
#424
b11010101 $
0"
#425
b11010101 %
1"
#426
b11010110 $
0"
#427
b11010110 %
1"
#428
b11010111 $
0"
#429
b11010111 %
1"
#430
b11011000 $
0"
#431
b11011000 %
1"
#432
b11011001 $
0"
#433
b11011001 %
1"
#434
b11011010 $
0"
#435
b11011010 %
1"
#436
b11011011 $
0"
#437
b11011011 %
1"
#438
b11011100 $
0"
#439
b11011100 %
1"
#440
b11011101 $
0"
#441
b11011101 %
1"
#442
b11011110 $
0"
#443
b11011110 %
1"
#444
b11011111 $
0"
#445
b11011111 %
1"
#446
b11100000 $
0"
#447
b11100000 %
1"
#448
b11100001 $
0"
#449
b11100001 %
1"
#450
b11100010 $
0"
#451
b11100010 %
1"
#452
b11100011 $
0"
#453
b11100011 %
1"
#454
b11100100 $
0"
#455
b11100100 %
1"
#456
b11100101 $
0"
#457
b11100101 %
1"
#458
b11100110 $
0"
#459
b11100110 %
1"
#460
b11100111 $
0"
#461
b11100111 %
1"
#462
b11101000 $
0"
#463
b11101000 %
1"
#464
b11101001 $
0"
#465
b11101001 %
1"
#466
b11101010 $
0"
#467
b11101010 %
1"
#468
b11101011 $
0"
#469
b11101011 %
1"
#470
b11101100 $
0"
#471
b11101100 %
1"
#472
b11101101 $
0"
#473
b11101101 %
1"
#474
b11101110 $
0"
#475
b11101110 %
1"
#476
b11101111 $
0"
#477
b11101111 %
1"
#478
b11110000 $
0"
#479
b11110000 %
1"
#480
b11110001 $
0"
#481
b11110001 %
1"
#482
b11110010 $
0"
#483
b11110010 %
1"
#484
b11110011 $
0"
#485
b11110011 %
1"
#486
b11110100 $
0"
#487
b11110100 %
1"
#488
b11110101 $
0"
#489
b11110101 %
1"
#490
b11110110 $
0"
#491
b11110110 %
1"
#492
b11110111 $
0"
#493
b11110111 %
1"
#494
b11111000 $
0"
#495
b11111000 %
1"
#496
b11111001 $
0"
#497
b11111001 %
1"
#498
b11111010 $
0"
#499
b11111010 %
1"
#500
b11111011 $
0"
#501
b11111011 %
1"
#502
b11111100 $
0"
#503
b11111100 %
1"
#504
b11111101 $
0"
#505
b11111101 %
1"
#506
b11111110 $
0"
#507
b11111110 %
1"
#508
b11111111 $
0"
#509
b11111111 %
1"
#510
b100000000 $
0"
#511
b100000000 %
1"
#512
b100000001 $
0"
#513
b100000001 %
1"
#514
b100000010 $
0"
#515
b100000010 %
1"
#516
b100000011 $
0"
#517
b100000011 %
1"
#518
b100000100 $
0"
#519
b100000100 %
1"
#520
b100000101 $
0"
#521
b100000101 %
1"
#522
b100000110 $
0"
#523
b100000110 %
1"
#524
b100000111 $
0"
#525
b100000111 %
1"
#526
b100001000 $
0"
#527
b100001000 %
1"
#528
b100001001 $
0"
#529
b100001001 %
1"
#530
b100001010 $
0"
#531
b100001010 %
1"
#532
b100001011 $
0"
#533
b100001011 %
1"
#534
b100001100 $
0"
#535
b100001100 %
1"
#536
b100001101 $
0"
#537
b100001101 %
1"
#538
b100001110 $
0"
#539
b100001110 %
1"
#540
b100001111 $
0"
#541
b100001111 %
1"
#542
b100010000 $
0"
#543
b100010000 %
1"
#544
b100010001 $
0"
#545
b100010001 %
1"
#546
b100010010 $
0"
#547
b100010010 %
1"
#548
b100010011 $
0"
#549
b100010011 %
1"
#550
b100010100 $
0"
#551
b100010100 %
1"
#552
b100010101 $
0"
#553
b100010101 %
1"
#554
b100010110 $
0"
#555
b100010110 %
1"
#556
b100010111 $
0"
#557
b100010111 %
1"
#558
b100011000 $
0"
#559
b100011000 %
1"
#560
b100011001 $
0"
#561
b100011001 %
1"
#562
b100011010 $
0"
#563
b100011010 %
1"
#564
b100011011 $
0"
#565
b100011011 %
1"
#566
b100011100 $
0"
#567
b100011100 %
1"
#568
b100011101 $
0"
#569
b100011101 %
1"
#570
b100011110 $
0"
#571
b100011110 %
1"
#572
b100011111 $
0"
#573
b100011111 %
1"
#574
b100100000 $
0"
#575
b100100000 %
1"
#576
b100100001 $
0"
#577
b100100001 %
1"
#578
b100100010 $
0"
#579
b100100010 %
1"
#580
b100100011 $
0"
#581
b100100011 %
1"
#582
b100100100 $
0"
#583
b100100100 %
1"
#584
b100100101 $
0"
#585
b100100101 %
1"
#586
b100100110 $
0"
#587
b100100110 %
1"
#588
b100100111 $
0"
#589
b100100111 %
1"
#590
b100101000 $
0"
#591
b100101000 %
1"
#592
b100101001 $
0"
#593
b100101001 %
1"
#594
b100101010 $
0"
#595
b100101010 %
1"
#596
b100101011 $
0"
#597
b100101011 %
1"
#598
b100101100 $
0"
#599
b100101100 %
1"
#600
b100101101 $
0"
#601
b100101101 %
1"
#602
b100101110 $
0"
#603
b100101110 %
1"
#604
b100101111 $
0"
#605
b100101111 %
1"
#606
b100110000 $
0"
#607
b100110000 %
1"
#608
b100110001 $
0"
#609
b100110001 %
1"
#610
b100110010 $
0"
#611
b100110010 %
1"
#612
b100110011 $
0"
#613
b100110011 %
1"
#614
b100110100 $
0"
#615
b100110100 %
1"
#616
b100110101 $
0"
#617
b100110101 %
1"
#618
b100110110 $
0"
#619
b100110110 %
1"
#620
b100110111 $
0"
#621
b100110111 %
1"
#622
b100111000 $
0"
#623
b100111000 %
1"
#624
b100111001 $
0"
#625
b100111001 %
1"
#626
b100111010 $
0"
#627
b100111010 %
1"
#628
b100111011 $
0"
#629
b100111011 %
1"
#630
b100111100 $
0"
#631
b100111100 %
1"
#632
b100111101 $
0"
#633
b100111101 %
1"
#634
b100111110 $
0"
#635
b100111110 %
1"
#636
b100111111 $
0"
#637
b100111111 %
1"
#638
b101000000 $
0"
#639
b101000000 %
1"
#640
b101000001 $
0"
#641
b101000001 %
1"
#642
b101000010 $
0"
#643
b101000010 %
1"
#644
b101000011 $
0"
#645
b101000011 %
1"
#646
b101000100 $
0"
#647
b101000100 %
1"
#648
b101000101 $
0"
#649
b101000101 %
1"
#650
b101000110 $
0"
#651
b101000110 %
1"
#652
b101000111 $
0"
#653
b101000111 %
1"
#654
b101001000 $
0"
#655
b101001000 %
1"
#656
b101001001 $
0"
#657
b101001001 %
1"
#658
b101001010 $
0"
#659
b101001010 %
1"
#660
b101001011 $
0"
#661
b101001011 %
1"
#662
b101001100 $
0"
#663
b101001100 %
1"
#664
b101001101 $
0"
#665
b101001101 %
1"
#666
b101001110 $
0"
#667
b101001110 %
1"
#668
b101001111 $
0"
#669
b101001111 %
1"
#670
b101010000 $
0"
#671
b101010000 %
1"
#672
b101010001 $
0"
#673
b101010001 %
1"
#674
b101010010 $
0"
#675
b101010010 %
1"
#676
b101010011 $
0"
#677
b101010011 %
1"
#678
b101010100 $
0"
#679
b101010100 %
1"
#680
b101010101 $
0"
#681
b101010101 %
1"
#682
b101010110 $
0"
#683
b101010110 %
1"
#684
b101010111 $
0"
#685
b101010111 %
1"
#686
b101011000 $
0"
#687
b101011000 %
1"
#688
b101011001 $
0"
#689
b101011001 %
1"
#690
b101011010 $
0"
#691
b101011010 %
1"
#692
b101011011 $
0"
#693
b101011011 %
1"
#694
b101011100 $
0"
#695
b101011100 %
1"
#696
b101011101 $
0"
#697
b101011101 %
1"
#698
b101011110 $
0"
#699
b101011110 %
1"
#700
b101011111 $
0"
#701
b101011111 %
1"
#702
b101100000 $
0"
#703
b101100000 %
1"
#704
b101100001 $
0"
#705
b101100001 %
1"
#706
b101100010 $
0"
#707
b101100010 %
1"
#708
b101100011 $
0"
#709
b101100011 %
1"
#710
b101100100 $
0"
#711
b101100100 %
1"
#712
b101100101 $
0"
#713
b101100101 %
1"
#714
b101100110 $
0"
#715
b101100110 %
1"
#716
b101100111 $
0"
#717
b101100111 %
1"
#718
b101101000 $
0"
#719
b101101000 %
1"
#720
b101101001 $
0"
#721
b101101001 %
1"
#722
b101101010 $
0"
#723
b101101010 %
1"
#724
b101101011 $
0"
#725
b101101011 %
1"
#726
b101101100 $
0"
#727
b101101100 %
1"
#728
b101101101 $
0"
#729
b101101101 %
1"
#730
b101101110 $
0"
#731
b101101110 %
1"
#732
b101101111 $
0"
#733
b101101111 %
1"
#734
b101110000 $
0"
#735
b101110000 %
1"
#736
b101110001 $
0"
#737
b101110001 %
1"
#738
b101110010 $
0"
#739
b101110010 %
1"
#740
b101110011 $
0"
#741
b101110011 %
1"
#742
b101110100 $
0"
#743
b101110100 %
1"
#744
b101110101 $
0"
#745
b101110101 %
1"
#746
b101110110 $
0"
#747
b101110110 %
1"
#748
b101110111 $
0"
#749
b101110111 %
1"
#750
b101111000 $
0"
#751
b101111000 %
1"
#752
b101111001 $
0"
#753
b101111001 %
1"
#754
b101111010 $
0"
#755
b101111010 %
1"
#756
b101111011 $
0"
#757
b101111011 %
1"
#758
b101111100 $
0"
#759
b101111100 %
1"
#760
b101111101 $
0"
#761
b101111101 %
1"
#762
b101111110 $
0"
#763
b101111110 %
1"
#764
b101111111 $
0"
#765
b101111111 %
1"
#766
b110000000 $
0"
#767
b110000000 %
1"
#768
b110000001 $
0"
#769
b110000001 %
1"
#770
b110000010 $
0"
#771
b110000010 %
1"
#772
b110000011 $
0"
#773
b110000011 %
1"
#774
b110000100 $
0"
#775
b110000100 %
1"
#776
b110000101 $
0"
#777
b110000101 %
1"
#778
b110000110 $
0"
#779
b110000110 %
1"
#780
b110000111 $
0"
#781
b110000111 %
1"
#782
b110001000 $
0"
#783
b110001000 %
1"
#784
b110001001 $
0"
#785
b110001001 %
1"
#786
b110001010 $
0"
#787
b110001010 %
1"
#788
b110001011 $
0"
#789
b110001011 %
1"
#790
b110001100 $
0"
#791
b110001100 %
1"
#792
b110001101 $
0"
#793
b110001101 %
1"
#794
b110001110 $
0"
#795
b110001110 %
1"
#796
b110001111 $
0"
#797
b110001111 %
1"
#798
b110010000 $
0"
#799
b110010000 %
1"
#800
b110010001 $
0"
#801
b110010001 %
1"
#802
b110010010 $
0"
#803
b110010010 %
1"
#804
b110010011 $
0"
#805
b110010011 %
1"
#806
b110010100 $
0"
#807
b110010100 %
1"
#808
b110010101 $
0"
#809
b110010101 %
1"
#810
b110010110 $
0"
#811
b110010110 %
1"
#812
b110010111 $
0"
#813
b110010111 %
1"
#814
b110011000 $
0"
#815
b110011000 %
1"
#816
b110011001 $
0"
#817
b110011001 %
1"
#818
b110011010 $
0"
#819
b110011010 %
1"
#820
b110011011 $
0"
#821
b110011011 %
1"
#822
b110011100 $
0"
#823
b110011100 %
1"
#824
b110011101 $
0"
#825
b110011101 %
1"
#826
b110011110 $
0"
#827
b110011110 %
1"
#828
b110011111 $
0"
#829
b110011111 %
1"
#830
b110100000 $
0"
#831
b110100000 %
1"
#832
b110100001 $
0"
#833
b110100001 %
1"
#834
b110100010 $
0"
#835
b110100010 %
1"
#836
b110100011 $
0"
#837
b110100011 %
1"
#838
b110100100 $
0"
#839
b110100100 %
1"
#840
b110100101 $
0"
#841
b110100101 %
1"
#842
b110100110 $
0"
#843
b110100110 %
1"
#844
b110100111 $
0"
#845
b110100111 %
1"
#846
b110101000 $
0"
#847
b110101000 %
1"
#848
b110101001 $
0"
#849
b110101001 %
1"
#850
b110101010 $
0"
#851
b110101010 %
1"
#852
b110101011 $
0"
#853
b110101011 %
1"
#854
b110101100 $
0"
#855
b110101100 %
1"
#856
b110101101 $
0"
#857
b110101101 %
1"
#858
b110101110 $
0"
#859
b110101110 %
1"
#860
b110101111 $
0"
#861
b110101111 %
1"
#862
b110110000 $
0"
#863
b110110000 %
1"
#864
b110110001 $
0"
#865
b110110001 %
1"
#866
b110110010 $
0"
#867
b110110010 %
1"
#868
b110110011 $
0"
#869
b110110011 %
1"
#870
b110110100 $
0"
#871
b110110100 %
1"
#872
b110110101 $
0"
#873
b110110101 %
1"
#874
b110110110 $
0"
#875
b110110110 %
1"
#876
b110110111 $
0"
#877
b110110111 %
1"
#878
b110111000 $
0"
#879
b110111000 %
1"
#880
b110111001 $
0"
#881
b110111001 %
1"
#882
b110111010 $
0"
#883
b110111010 %
1"
#884
b110111011 $
0"
#885
b110111011 %
1"
#886
b110111100 $
0"
#887
b110111100 %
1"
#888
b110111101 $
0"
#889
b110111101 %
1"
#890
b110111110 $
0"
#891
b110111110 %
1"
#892
b110111111 $
0"
#893
b110111111 %
1"
#894
b111000000 $
0"
#895
b111000000 %
1"
#896
b111000001 $
0"
#897
b111000001 %
1"
#898
b111000010 $
0"
#899
b111000010 %
1"
#900
b111000011 $
0"
#901
b111000011 %
1"
#902
b111000100 $
0"
#903
b111000100 %
1"
#904
b111000101 $
0"
#905
b111000101 %
1"
#906
b111000110 $
0"
#907
b111000110 %
1"
#908
b111000111 $
0"
#909
b111000111 %
1"
#910
b111001000 $
0"
#911
b111001000 %
1"
#912
b111001001 $
0"
#913
b111001001 %
1"
#914
b111001010 $
0"
#915
b111001010 %
1"
#916
b111001011 $
0"
#917
b111001011 %
1"
#918
b111001100 $
0"
#919
b111001100 %
1"
#920
b111001101 $
0"
#921
b111001101 %
1"
#922
b111001110 $
0"
#923
b111001110 %
1"
#924
b111001111 $
0"
#925
b111001111 %
1"
#926
b111010000 $
0"
#927
b111010000 %
1"
#928
b111010001 $
0"
#929
b111010001 %
1"
#930
b111010010 $
0"
#931
b111010010 %
1"
#932
b111010011 $
0"
#933
b111010011 %
1"
#934
b111010100 $
0"
#935
b111010100 %
1"
#936
b111010101 $
0"
#937
b111010101 %
1"
#938
b111010110 $
0"
#939
b111010110 %
1"
#940
b111010111 $
0"
#941
b111010111 %
1"
#942
b111011000 $
0"
#943
b111011000 %
1"
#944
b111011001 $
0"
#945
b111011001 %
1"
#946
b111011010 $
0"
#947
b111011010 %
1"
#948
b111011011 $
0"
#949
b111011011 %
1"
#950
b111011100 $
0"
#951
b111011100 %
1"
#952
b111011101 $
0"
#953
b111011101 %
1"
#954
b111011110 $
0"
#955
b111011110 %
1"
#956
b111011111 $
0"
#957
b111011111 %
1"
#958
b111100000 $
0"
#959
b111100000 %
1"
#960
b111100001 $
0"
#961
b111100001 %
1"
#962
b111100010 $
0"
#963
b111100010 %
1"
#964
b111100011 $
0"
#965
b111100011 %
1"
#966
b111100100 $
0"
#967
b111100100 %
1"
#968
b111100101 $
0"
#969
b111100101 %
1"
#970
b111100110 $
0"
#971
b111100110 %
1"
#972
b111100111 $
0"
#973
b111100111 %
1"
#974
b111101000 $
0"
#975
b111101000 %
1"
#976
b111101001 $
0"
#977
b111101001 %
1"
#978
b111101010 $
0"
#979
b111101010 %
1"
#980
b111101011 $
0"
#981
b111101011 %
1"
#982
b111101100 $
0"
#983
b111101100 %
1"
#984
b111101101 $
0"
#985
b111101101 %
1"
#986
b111101110 $
0"
#987
b111101110 %
1"
#988
b111101111 $
0"
#989
b111101111 %
1"
#990
b111110000 $
0"
#991
b111110000 %
1"
#992
b111110001 $
0"
#993
b111110001 %
1"
#994
b111110010 $
0"
#995
b111110010 %
1"
#996
b111110011 $
0"
#997
b111110011 %
1"
#998
b111110100 $
0"
#999
b111110100 %
1"
#1000
b111110101 $
0"
#1001
b111110101 %
1"
#1002
b111110110 $
0"
#1003
b111110110 %
1"
#1004
b111110111 $
0"
#1005
b111110111 %
1"
#1006
b111111000 $
0"
#1007
b111111000 %
1"
#1008
b111111001 $
0"
#1009
b111111001 %
1"
#1010
b111111010 $
0"
#1011
b111111010 %
1"
#1012
b111111011 $
0"
#1013
b111111011 %
1"
#1014
b111111100 $
0"
#1015
b111111100 %
1"
#1016
b111111101 $
0"
#1017
b111111101 %
1"
#1018
b111111110 $
0"
#1019
b111111110 %
1"
#1020
b111111111 $
0"
#1021
b111111111 %
1"
#1022
b1000000000 $
0"
#1023
b1000000000 %
1"
#1024
b1000000001 $
0"
#1025
b1000000001 %
1"
#1026
b1000000010 $
0"
#1027
b1000000010 %
1"
#1028
b1000000011 $
0"
#1029
b1000000011 %
1"
#1030
b1000000100 $
0"
#1031
b1000000100 %
1"
#1032
b1000000101 $
0"
#1033
b1000000101 %
1"
#1034
b1000000110 $
0"
#1035
b1000000110 %
1"
#1036
b1000000111 $
0"
#1037
b1000000111 %
1"
#1038
b1000001000 $
0"
#1039
b1000001000 %
1"
#1040
b1000001001 $
0"
#1041
b1000001001 %
1"
#1042
b1000001010 $
0"
#1043
b1000001010 %
1"
#1044
b1000001011 $
0"
#1045
b1000001011 %
1"
#1046
b1000001100 $
0"
#1047
b1000001100 %
1"
#1048
b1000001101 $
0"
#1049
b1000001101 %
1"
#1050
b1000001110 $
0"
#1051
b1000001110 %
1"
#1052
b1000001111 $
0"
#1053
b1000001111 %
1"
#1054
b1000010000 $
0"
#1055
b1000010000 %
1"
#1056
b1000010001 $
0"
#1057
b1000010001 %
1"
#1058
b1000010010 $
0"
#1059
b1000010010 %
1"
#1060
b1000010011 $
0"
#1061
b1000010011 %
1"
#1062
b1000010100 $
0"
#1063
b1000010100 %
1"
#1064
b1000010101 $
0"
#1065
b1000010101 %
1"
#1066
b1000010110 $
0"
#1067
b1000010110 %
1"
#1068
b1000010111 $
0"
