examples/UnoLite/max240/frqdivmod.v
module frqdivmod(clk, s_out);
parameter DIV=2;
// calculated parameters
parameter WITH = ($clog2(DIV+1)>0) ? $clog2(DIV+1) : 1;

input wire clk;
output wire s_out;

reg clk_n; 

reg [(WITH-1):0] pos_cnt; 
reg [(WITH-1):0] neg_cnt; 

wire [(WITH-1):0] div_value = DIV[(WITH-1):0];

initial begin
	clk_n <= 1'b0;
	pos_cnt <= {(WITH){1'b0}};
	neg_cnt <= {(WITH){1'b0}};
end

assign s_out = (DIV==1) ? clk : clk_n;

always @ (posedge clk) begin
	pos_cnt <= (pos_cnt + 1'b1) % div_value;
end

always @ (negedge clk) begin
	neg_cnt <= (neg_cnt + 1'b1) % div_value;
end

always @(clk, pos_cnt, neg_cnt) begin //pos_cnt in sens list addd for resolve warning "variable is read inside the Always Construct but isn't in the Always Construct's Event Control"
	if ((DIV%2) == 1'b0) begin
		clk_n <= ( pos_cnt >= (DIV/2)) ? 1'b1 : 1'b0;
	end else begin
		clk_n <= (( pos_cnt > (DIV/2)) || ( neg_cnt > (DIV/2))) ? 1'b1 : 1'b0;
	end
end
	
endmodule

examples/UnoLite/test/testbench.v
module testbench();

reg clk;

wire [11:0] out;

wire out1;
reg [7:0] period;

frqdivmod  #(.DIV(3)) div1(.clk(clk), .s_out(out1));

//div3
reg [1:0] d3_r; initial d3_r <= 2'd0;
always @ (posedge clk) begin
	d3_r <= (d3_r==2'd2) ? 2'd0 : d3_r + 1'b1;
end
wire res_d3 = (d3_r==2'd0);

initial
begin
	period <= 8'd0;
    $dumpfile("bench.vcd");
    $dumpvars(0,testbench);

    $display("starting testbench!!!!");
	
	

	clk <= 0;
	repeat (1000) begin
		#10;
		clk <= 1;
		#10;
		clk <= 0;
		period <= period + 1'b1;
	end
	
    $display("finished OK!");
    $finish;
end


	
endmodule

examples/UnoLite/test/bench.vcd
$date
	Wed Oct 12 20:53:32 2016
$end
$version
	Icarus Verilog
$end
$timescale
	1s
$end
$scope module testbench $end
$var wire 1 ! res_d3 $end
$var wire 1 " out1 $end
$var reg 1 # clk $end
$var reg 2 $ d3_r [1:0] $end
$var reg 8 % period [7:0] $end
$scope module div1 $end
$var wire 1 # clk $end
$var wire 2 & div_value [1:0] $end
$var wire 1 " s_out $end
$var reg 1 ' clk_n $end
$var reg 2 ( neg_cnt [1:0] $end
$var reg 2 ) pos_cnt [1:0] $end
$upscope $end
$upscope $end
$enddefinitions $end
#0
$dumpvars
b0 )
b1 (
0'
b11 &
b0 %
b0 $
0#
0"
1!
$end
#10
b1 )
0!
b1 $
1#
#20
1"
1'
b10 (
b1 %
0#
#30
b10 $
b10 )
1#
#40
b0 (
b10 %
0#
#50
0"
0'
b0 )
1!
b0 $
1#
#60
b1 (
b11 %
0#
#70
0!
b1 $
b1 )
1#
#80
1"
1'
b10 (
b100 %
0#
#90
b10 )
b10 $
1#
#100
b0 (
b101 %
0#
#110
0"
0'
1!
b0 $
b0 )
1#
#120
b1 (
b110 %
0#
#130
b1 )
0!
b1 $
1#
#140
1"
1'
b10 (
b111 %
0#
#150
b10 $
b10 )
1#
#160
b0 (
b1000 %
0#
#170
0"
0'
b0 )
1!
b0 $
1#
#180
b1 (
b1001 %
0#
#190
0!
b1 $
b1 )
1#
#200
1"
1'
b10 (
b1010 %
0#
#210
b10 )
b10 $
1#
#220
b0 (
b1011 %
0#
#230
0"
0'
1!
b0 $
b0 )
1#
#240
b1 (
b1100 %
0#
#250
b1 )
0!
b1 $
1#
#260
1"
1'
b10 (
b1101 %
0#
#270
b10 $
b10 )
1#
#280
b0 (
b1110 %
0#
#290
0"
0'
b0 )
1!
b0 $
1#
#300
b1 (
b1111 %
0#
#310
0!
b1 $
b1 )
1#
#320
1"
1'
b10 (
b10000 %
0#
#330
b10 )
b10 $
1#
#340
b0 (
b10001 %
0#
#350
0"
0'
1!
b0 $
b0 )
1#
#360
b1 (
b10010 %
0#
#370
b1 )
0!
b1 $
1#
#380
1"
1'
b10 (
b10011 %
0#
#390
b10 $
b10 )
1#
#400
b0 (
b10100 %
0#
#410
0"
0'
b0 )
1!
b0 $
1#
#420
b1 (
b10101 %
0#
#430
0!
b1 $
b1 )
1#
#440
1"
1'
b10 (
b10110 %
0#
#450
b10 )
b10 $
1#
#460
b0 (
b10111 %
0#
#470
0"
0'
1!
b0 $
b0 )
1#
#480
b1 (
b11000 %
0#
#490
b1 )
0!
b1 $
1#
#500
1"
1'
b10 (
b11001 %
0#
#510
b10 $
b10 )
1#
#520
b0 (
b11010 %
0#
#530
0"
0'
b0 )
1!
b0 $
1#
#540
b1 (
b11011 %
0#
#550
0!
b1 $
b1 )
1#
#560
1"
1'
b10 (
b11100 %
0#
#570
b10 )
b10 $
1#
#580
b0 (
b11101 %
0#
#590
0"
0'
1!
b0 $
b0 )
1#
#600
b1 (
b11110 %
0#
#610
b1 )
0!
b1 $
1#
#620
1"
1'
b10 (
b11111 %
0#
#630
b10 $
b10 )
1#
#640
b0 (
b100000 %
0#
#650
0"
0'
b0 )
1!
b0 $
1#
#660
b1 (
b100001 %
0#
#670
0!
b1 $
b1 )
1#
#680
1"
1'
b10 (
b100010 %
0#
#690
b10 )
b10 $
1#
#700
b0 (
b100011 %
0#
#710
0"
0'
1!
b0 $
b0 )
1#
#720
b1 (
b100100 %
0#
#730
b1 )
0!
b1 $
1#
#740
1"
1'
b10 (
b100101 %
0#
#750
b10 $
b10 )
1#
#760
b0 (
b100110 %
0#
#770
0"
0'
b0 )
1!
b0 $
1#
#780
b1 (
b100111 %
0#
#790
0!
b1 $
b1 )
1#
#800
1"
1'
b10 (
b101000 %
0#
#810
b10 )
b10 $
1#
#820
b0 (
b101001 %
0#
#830
0"
0'
1!
b0 $
b0 )
1#
#840
b1 (
b101010 %
0#
#850
b1 )
0!
b1 $
1#
#860
1"
1'
b10 (
b101011 %
0#
#870
b10 $
b10 )
1#
#880
b0 (
b101100 %
0#
#890
0"
0'
b0 )
1!
b0 $
1#
#900
b1 (
b101101 %
0#
#910
0!
b1 $
b1 )
1#
#920
1"
1'
b10 (
b101110 %
0#
#930
b10 )
b10 $
1#
#940
b0 (
b101111 %
0#
#950
0"
0'
1!
b0 $
b0 )
1#
#960
b1 (
b110000 %
0#
#970
b1 )
0!
b1 $
1#
#980
1"
1'
b10 (
b110001 %
0#
#990
b10 $
b10 )
1#
#1000
b0 (
b110010 %
0#
#1010
0"
0'
b0 )
1!
b0 $
1#
#1020
b1 (
b110011 %
0#
#1030
0!
b1 $
b1 )
1#
#1040
1"
1'
b10 (
b110100 %
0#
#1050
b10 )
b10 $
1#
#1060
b0 (
b110101 %
0#
#1070
0"
0'
1!
b0 $
b0 )
1#
#1080
b1 (
b110110 %
0#
#1090
b1 )
0!
b1 $
1#
#1100
1"
1'
b10 (
b110111 %
0#
#1110
b10 $
b10 )
1#
#1120
b0 (
b111000 %
0#
#1130
0"
0'
b0 )
1!
b0 $
1#
#1140
b1 (
b111001 %
0#
#1150
0!
b1 $
b1 )
1#
#1160
1"
1'
b10 (
b111010 %
0#
#1170
b10 )
b10 $
1#
#1180
b0 (
b111011 %
0#
#1190
0"
0'
1!
b0 $
b0 )
1#
#1200
b1 (
b111100 %
0#
#1210
b1 )
0!
b1 $
1#
#1220
1"
1'
b10 (
b111101 %
0#
#1230
b10 $
b10 )
1#
#1240
b0 (
b111110 %
0#
#1250
0"
0'
b0 )
1!
b0 $
1#
#1260
b1 (
b111111 %
0#
#1270
0!
b1 $
b1 )
1#
#1280
1"
1'
b10 (
b1000000 %
0#
#1290
b10 )
b10 $
1#
#1300
b0 (
b1000001 %
0#
#1310
0"
0'
1!
b0 $
b0 )
1#
#1320
b1 (
b1000010 %
0#
#1330
b1 )
0!
b1 $
1#
#1340
1"
1'
b10 (
b1000011 %
0#
#1350
b10 $
b10 )
1#
#1360
b0 (
b1000100 %
0#
#1370
0"
0'
b0 )
1!
b0 $
1#
#1380
b1 (
b1000101 %
0#
#1390
0!
b1 $
b1 )
1#
#1400
1"
1'
b10 (
b1000110 %
0#
#1410
b10 )
b10 $
1#
#1420
b0 (
b1000111 %
0#
#1430
0"
0'
1!
b0 $
b0 )
1#
#1440
b1 (
b1001000 %
0#
#1450
b1 )
0!
b1 $
1#
#1460
1"
1'
b10 (
b1001001 %
0#
#1470
b10 $
b10 )
1#
#1480
b0 (
b1001010 %
0#
#1490
0"
0'
b0 )
1!
b0 $
1#
#1500
b1 (
b1001011 %
0#
#1510
0!
b1 $
b1 )
1#
#1520
1"
1'
b10 (
b1001100 %
0#
#1530
b10 )
b10 $
1#
#1540
b0 (
b1001101 %
0#
#1550
0"
0'
1!
b0 $
b0 )
1#
#1560
b1 (
b1001110 %
0#
#1570
b1 )
0!
b1 $
1#
#1580
1"
1'
b10 (
b1001111 %
0#
#1590
b10 $
b10 )
1#
#1600
b0 (
b1010000 %
0#
#1610
0"
0'
b0 )
1!
b0 $
1#
#1620
b1 (
b1010001 %
0#
#1630
0!
b1 $
b1 )
1#
#1640
1"
1'
b10 (
b1010010 %
0#
#1650
b10 )
b10 $
1#
#1660
b0 (
b1010011 %
0#
#1670
0"
0'
1!
b0 $
b0 )
1#
#1680
b1 (
b1010100 %
0#
#1690
b1 )
0!
b1 $
1#
#1700
1"
1'
b10 (
b1010101 %
0#
#1710
b10 $
b10 )
1#
#1720
b0 (
b1010110 %
0#
#1730
0"
0'
b0 )
1!
b0 $
1#
#1740
b1 (
b1010111 %
0#
#1750
0!
b1 $
b1 )
1#
#1760
1"
1'
b10 (
b1011000 %
0#
#1770
b10 )
b10 $
1#
#1780
b0 (
b1011001 %
0#
#1790
0"
0'
1!
b0 $
b0 )
1#
#1800
b1 (
b1011010 %
0#
#1810
b1 )
0!
b1 $
1#
#1820
1"
1'
b10 (
b1011011 %
0#
#1830
b10 $
b10 )
1#
#1840
b0 (
b1011100 %
0#
#1850
0"
0'
b0 )
1!
b0 $
1#
#1860
b1 (
b1011101 %
0#
#1870
0!
b1 $
b1 )
1#
#1880
1"
1'
b10 (
b1011110 %
0#
#1890
b10 )
b10 $
1#
#1900
b0 (
b1011111 %
0#
#1910
0"
0'
1!
b0 $
b0 )
1#
#1920
b1 (
b1100000 %
0#
#1930
b1 )
0!
b1 $
1#
#1940
1"
1'
b10 (
b1100001 %
0#
#1950
b10 $
b10 )
1#
#1960
b0 (
b1100010 %
0#
#1970
0"
0'
b0 )
1!
b0 $
1#
#1980
b1 (
b1100011 %
0#
#1990
0!
b1 $
b1 )
1#
#2000
1"
1'
b10 (
b1100100 %
0#
#2010
b10 )
b10 $
1#
#2020
b0 (
b1100101 %
0#
#2030
0"
0'
1!
b0 $
b0 )
1#
#2040
b1 (
b1100110 %
0#
#2050
b1 )
0!
b1 $
1#
#2060
1"
1'
b10 (
b1100111 %
0#
#2070
b10 $
b10 )
1#
#2080
b0 (
b1101000 %
0#
#2090
0"
0'
b0 )
1!
b0 $
1#
#2100
b1 (
b1101001 %
0#
#2110
0!
b1 $
b1 )
1#
#2120
1"
1'
b10 (
b1101010 %
0#
#2130
b10 )
b10 $
1#
#2140
b0 (
b1101011 %
0#
#2150
0"
0'
1!
b0 $
b0 )
1#
#2160
b1 (
b1101100 %
0#
#2170
b1 )
0!
b1 $
1#
#2180
1"
1'
b10 (
b1101101 %
0#
#2190
b10 $
b10 )
1#
#2200
b0 (
b1101110 %
0#
#2210
0"
0'
b0 )
1!
b0 $
1#
#2220
b1 (
b1101111 %
0#
#2230
0!
b1 $
b1 )
1#
#2240
1"
1'
b10 (
b1110000 %
0#
#2250
b10 )
b10 $
1#
#2260
b0 (
b1110001 %
0#
#2270
0"
0'
1!
b0 $
b0 )
1#
#2280
b1 (
b1110010 %
0#
#2290
b1 )
0!
b1 $
1#
#2300
1"
1'
b10 (
b1110011 %
0#
#2310
b10 $
b10 )
1#
#2320
b0 (
b1110100 %
0#
#2330
0"
0'
b0 )
1!
b0 $
1#
#2340
b1 (
b1110101 %
0#
#2350
0!
b1 $
b1 )
1#
#2360
1"
1'
b10 (
b1110110 %
0#
#2370
b10 )
b10 $
1#
#2380
b0 (
b1110111 %
0#
#2390
0"
0'
1!
b0 $
b0 )
1#
#2400
b1 (
b1111000 %
0#
#2410
b1 )
0!
b1 $
1#
#2420
1"
1'
b10 (
b1111001 %
0#
#2430
b10 $
b10 )
1#
#2440
b0 (
b1111010 %
0#
#2450
0"
0'
b0 )
1!
b0 $
1#
#2460
b1 (
b1111011 %
0#
#2470
0!
b1 $
b1 )
1#
#2480
1"
1'
b10 (
b1111100 %
0#
#2490
b10 )
b10 $
1#
#2500
b0 (
b1111101 %
0#
#2510
0"
0'
1!
b0 $
b0 )
1#
#2520
b1 (
b1111110 %
0#
#2530
b1 )
0!
b1 $
1#
#2540
1"
1'
b10 (
b1111111 %
0#
#2550
b10 $
b10 )
1#
#2560
b0 (
b10000000 %
0#
#2570
0"
0'
b0 )
1!
b0 $
1#
#2580
b1 (
b10000001 %
0#
#2590
0!
b1 $
b1 )
1#
#2600
1"
1'
b10 (
b10000010 %
0#
#2610
b10 )
b10 $
1#
#2620
b0 (
b10000011 %
0#
#2630
0"
0'
1!
b0 $
b0 )
1#
#2640
b1 (
b10000100 %
0#
#2650
b1 )
0!
b1 $
1#
#2660
1"
1'
b10 (
b10000101 %
0#
#2670
b10 $
b10 )
1#
#2680
b0 (
b10000110 %
0#
#2690
0"
0'
b0 )
1!
b0 $
1#
#2700
b1 (
b10000111 %
0#
#2710
0!
b1 $
b1 )
1#
#2720
1"
1'
b10 (
b10001000 %
0#
#2730
b10 )
b10 $
1#
#2740
b0 (
b10001001 %
0#
#2750
0"
0'
1!
b0 $
b0 )
1#
#2760
b1 (
b10001010 %
0#
#2770
b1 )
0!
b1 $
1#
#2780
1"
1'
b10 (
b10001011 %
0#
#2790
b10 $
b10 )
1#
#2800
b0 (
b10001100 %
0#
#2810
0"
0'
b0 )
1!
b0 $
1#
#2820
b1 (
b10001101 %
0#
#2830
0!
b1 $
b1 )
1#
#2840
1"
1'
b10 (
b10001110 %
0#
#2850
b10 )
b10 $
1#
#2860
b0 (
b10001111 %
0#
#2870
0"
0'
1!
b0 $
b0 )
1#
#2880
b1 (
b10010000 %
0#
#2890
b1 )
0!
b1 $
1#
#2900
1"
1'
b10 (
b10010001 %
0#
#2910
b10 $
b10 )
1#
#2920
b0 (
b10010010 %
0#
#2930
0"
0'
b0 )
1!
b0 $
1#
#2940
b1 (
b10010011 %
0#
#2950
0!
b1 $
b1 )
1#
#2960
1"
1'
b10 (
b10010100 %
0#
#2970
b10 )
b10 $
1#
#2980
b0 (
b10010101 %
0#
#2990
0"
0'
1!
b0 $
b0 )
1#
#3000
b1 (
b10010110 %
0#
#3010
b1 )
0!
b1 $
1#
#3020
1"
1'
b10 (
b10010111 %
0#
#3030
b10 $
b10 )
1#
#3040
b0 (
b10011000 %
0#
#3050
0"
0'
b0 )
1!
b0 $
1#
#3060
b1 (
b10011001 %
0#
#3070
0!
b1 $
b1 )
1#
#3080
1"
1'
b10 (
b10011010 %
0#
#3090
b10 )
b10 $
1#
#3100
b0 (
b10011011 %
0#
#3110
0"
0'
1!
b0 $
b0 )
1#
#3120
b1 (
b10011100 %
0#
#3130
b1 )
0!
b1 $
1#
#3140
1"
1'
b10 (
b10011101 %
0#
#3150
b10 $
b10 )
1#
#3160
b0 (
b10011110 %
0#
#3170
0"
0'
b0 )
1!
b0 $
1#
#3180
b1 (
b10011111 %
0#
#3190
0!
b1 $
b1 )
1#
#3200
1"
1'
b10 (
b10100000 %
0#
#3210
b10 )
b10 $
1#
#3220
b0 (
b10100001 %
0#
#3230
0"
0'
1!
b0 $
b0 )
1#
#3240
b1 (
b10100010 %
0#
#3250
b1 )
0!
b1 $
1#
#3260
1"
1'
b10 (
b10100011 %
0#
#3270
b10 $
b10 )
1#
#3280
b0 (
b10100100 %
0#
#3290
0"
0'
b0 )
1!
b0 $
1#
#3300
b1 (
b10100101 %
0#
#3310
0!
b1 $
b1 )
1#
#3320
1"
1'
b10 (
b10100110 %
0#
#3330
b10 )
b10 $
1#
#3340
b0 (
b10100111 %
0#
#3350
0"
0'
1!
b0 $
b0 )
1#
#3360
b1 (
b10101000 %
0#
#3370
b1 )
0!
b1 $
1#
#3380
1"
1'
b10 (
b10101001 %
0#
#3390
b10 $
b10 )
1#
#3400
b0 (
b10101010 %
0#
#3410
0"
0'
b0 )
1!
b0 $
1#
#3420
b1 (
b10101011 %
0#
#3430
0!
b1 $
b1 )
1#
#3440
1"
1'
b10 (
b10101100 %
0#
#3450
b10 )
b10 $
1#
#3460
b0 (
b10101101 %
0#
#3470
0"
0'
1!
b0 $
b0 )
1#
#3480
b1 (
b10101110 %
0#
#3490
b1 )
0!
b1 $
1#
#3500
1"
1'
b10 (
b10101111 %
0#
#3510
b10 $
b10 )
1#
#3520
b0 (
b10110000 %
0#
#3530
0"
0'
b0 )
1!
b0 $
1#
#3540
b1 (
b10110001 %
0#
#3550
0!
b1 $
b1 )
1#
#3560
1"
1'
b10 (
b10110010 %
0#
#3570
b10 )
b10 $
1#
#3580
b0 (
b10110011 %
0#
#3590
0"
0'
1!
b0 $
b0 )
1#
#3600
b1 (
b10110100 %
0#
#3610
b1 )
0!
b1 $
1#
#3620
1"
1'
b10 (
b10110101 %
0#
#3630
b10 $
b10 )
1#
#3640
b0 (
b10110110 %
0#
#3650
0"
0'
b0 )
1!
b0 $
1#
#3660
b1 (
b10110111 %
0#
#3670
0!
b1 $
b1 )
1#
#3680
1"
1'
b10 (
b10111000 %
0#
#3690
b10 )
b10 $
1#
#3700
b0 (
b10111001 %
0#
#3710
0"
0'
1!
b0 $
b0 )
1#
#3720
b1 (
b10111010 %
0#
#3730
b1 )
0!
b1 $
1#
#3740
1"
1'
b10 (
b10111011 %
0#
#3750
b10 $
b10 )
1#
#3760
b0 (
b10111100 %
0#
#3770
0"
0'
b0 )
1!
b0 $
1#
#3780
b1 (
b10111101 %
0#
#3790
0!
b1 $
b1 )
1#
#3800
1"
1'
b10 (
b10111110 %
0#
#3810
b10 )
b10 $
1#
#3820
b0 (
b10111111 %
0#
#3830
0"
0'
1!
b0 $
b0 )
1#
#3840
b1 (
b11000000 %
0#
#3850
b1 )
0!
b1 $
1#
#3860
1"
1'
b10 (
b11000001 %
0#
#3870
b10 $
b10 )
1#
#3880
b0 (
b11000010 %
0#
#3890
0"
0'
b0 )
1!
b0 $
1#
#3900
b1 (
b11000011 %
0#
#3910
0!
b1 $
b1 )
1#
#3920
1"
1'
b10 (
b11000100 %
0#
#3930
b10 )
b10 $
1#
#3940
b0 (
b11000101 %
0#
#3950
0"
0'
1!
b0 $
b0 )
1#
#3960
b1 (
b11000110 %
0#
#3970
b1 )
0!
b1 $
1#
#3980
1"
1'
b10 (
b11000111 %
0#
#3990
b10 $
b10 )
1#
#4000
b0 (
b11001000 %
0#
#4010
0"
0'
b0 )
1!
b0 $
1#
#4020
b1 (
b11001001 %
0#
#4030
0!
b1 $
b1 )
1#
#4040
1"
1'
b10 (
b11001010 %
0#
#4050
b10 )
b10 $
1#
#4060
b0 (
b11001011 %
0#
#4070
0"
0'
1!
b0 $
b0 )
1#
#4080
b1 (
b11001100 %
0#
#4090
b1 )
0!
b1 $
1#
#4100
1"
1'
b10 (
b11001101 %
0#
#4110
b10 $
b10 )
1#
#4120
b0 (
b11001110 %
0#
#4130
0"
0'
b0 )
1!
b0 $
1#
#4140
b1 (
b11001111 %
0#
#4150
0!
b1 $
b1 )
1#
#4160
1"
1'
b10 (
b11010000 %
0#
#4170
b10 )
b10 $
1#
#4180
b0 (
b11010001 %
0#
#4190
0"
0'
1!
b0 $
b0 )
1#
#4200
b1 (
b11010010 %
0#
#4210
b1 )
0!
b1 $
1#
#4220
1"
1'
b10 (
b11010011 %
0#
#4230
b10 $
b10 )
1#
#4240
b0 (
b11010100 %
0#
#4250
0"
0'
b0 )
1!
b0 $
1#
#4260
b1 (
b11010101 %
0#
#4270
0!
b1 $
b1 )
1#
#4280
1"
1'
b10 (
b11010110 %
0#
#4290
b10 )
b10 $
1#
#4300
b0 (
b11010111 %
0#
#4310
0"
0'
1!
b0 $
b0 )
1#
#4320
b1 (
b11011000 %
0#
#4330
b1 )
0!
b1 $
1#
#4340
1"
1'
b10 (
b11011001 %
0#
#4350
b10 $
b10 )
1#
#4360
b0 (
b11011010 %
0#
#4370
0"
0'
b0 )
1!
b0 $
1#
#4380
b1 (
b11011011 %
0#
#4390
0!
b1 $
b1 )
1#
#4400
1"
1'
b10 (
b11011100 %
0#
#4410
b10 )
b10 $
1#
#4420
b0 (
b11011101 %
0#
#4430
0"
0'
1!
b0 $
b0 )
1#
#4440
b1 (
b11011110 %
0#
#4450
b1 )
0!
b1 $
1#
#4460
1"
1'
b10 (
b11011111 %
0#
#4470
b10 $
b10 )
1#
#4480
b0 (
b11100000 %
0#
#4490
0"
0'
b0 )
1!
b0 $
1#
#4500
b1 (
b11100001 %
0#
#4510
0!
b1 $
b1 )
1#
#4520
1"
1'
b10 (
b11100010 %
0#
#4530
b10 )
b10 $
1#
#4540
b0 (
b11100011 %
0#
#4550
0"
0'
1!
b0 $
b0 )
1#
#4560
b1 (
b11100100 %
0#
#4570
b1 )
0!
b1 $
1#
#4580
1"
1'
b10 (
b11100101 %
0#
#4590
b10 $
b10 )
1#
#4600
b0 (
b11100110 %
0#
#4610
0"
0'
b0 )
1!
b0 $
1#
#4620
b1 (
b11100111 %
0#
#4630
0!
b1 $
b1 )
1#
#4640
1"
1'
b10 (
b11101000 %
0#
#4650
b10 )
b10 $
1#
#4660
b0 (
b11101001 %
0#
#4670
0"
0'
1!
b0 $
b0 )
1#
#4680
b1 (
b11101010 %
0#
#4690
b1 )
0!
b1 $
1#
#4700
1"
1'
b10 (
b11101011 %
0#
#4710
b10 $
b10 )
1#
#4720
b0 (
b11101100 %
0#
#4730
0"
0'
b0 )
1!
b0 $
1#
#4740
b1 (
b11101101 %
0#
#4750
0!
b1 $
b1 )
1#
#4760
1"
1'
b10 (
b11101110 %
0#
#4770
b10 )
b10 $
1#
#4780
b0 (
b11101111 %
0#
#4790
0"
0'
1!
b0 $
b0 )
1#
#4800
b1 (
b11110000 %
0#
#4810
b1 )
0!
b1 $
1#
#4820
1"
1'
b10 (
b11110001 %
0#
#4830
b10 $
b10 )
1#
#4840
b0 (
b11110010 %
0#
#4850
0"
0'
b0 )
1!
b0 $
1#
#4860
b1 (
b11110011 %
0#
#4870
0!
b1 $
b1 )
1#
#4880
1"
1'
b10 (
b11110100 %
0#
#4890
b10 )
b10 $
1#
#4900
b0 (
b11110101 %
0#
#4910
0"
0'
1!
b0 $
b0 )
1#
#4920
b1 (
b11110110 %
0#
#4930
b1 )
0!
b1 $
1#
#4940
1"
1'
b10 (
b11110111 %
0#
#4950
b10 $
b10 )
1#
#4960
b0 (
b11111000 %
0#
#4970
0"
0'
b0 )
1!
b0 $
1#
#4980
b1 (
b11111001 %
0#
#4990
0!
b1 $
b1 )
1#
#5000
1"
1'
b10 (
b11111010 %
0#
#5010
b10 )
b10 $
1#
#5020
b0 (
b11111011 %
0#
#5030
0"
0'
1!
b0 $
b0 )
1#
#5040
b1 (
b11111100 %
0#
#5050
b1 )
0!
b1 $
1#
#5060
1"
1'
b10 (
b11111101 %
0#
#5070
b10 $
b10 )
1#
#5080
b0 (
b11111110 %
0#
#5090
0"
0'
b0 )
1!
b0 $
1#
#5100
b1 (
b11111111 %
0#
#5110
0!
b1 $
b1 )
1#
#5120
1"
1'
b10 (
b0 %
0#
#5130
b10 )
b10 $
1#
#5140
b0 (
b1 %
0#
#5150
0"
0'
1!
b0 $
b0 )
1#
#5160
b1 (
b10 %
0#
#5170
b1 )
0!
b1 $
1#
#5180
1"
1'
b10 (
b11 %
0#
#5190
b10 $
b10 )
1#
#5200
b0 (
b100 %
0#
#5210
0"
0'
b0 )
1!
b0 $
1#
#5220
b1 (
b101 %
0#
#5230
0!
b1 $
b1 )
1#
#5240
1"
1'
b10 (
b110 %
0#
#5250
b10 )
b10 $
1#
#5260
b0 (
b111 %
0#
#5270
0"
0'
1!
b0 $
b0 )
1#
#5280
b1 (
b1000 %
0#
#5290
b1 )
0!
b1 $
1#
#5300
1"
1'
b10 (
b1001 %
0#
#5310
b10 $
b10 )
1#
#5320
b0 (
b1010 %
0#
#5330
0"
0'
b0 )
1!
b0 $
1#
#5340
b1 (
b1011 %
0#
#5350
0!
b1 $
b1 )
1#
#5360
1"
1'
b10 (
b1100 %
0#
#5370
b10 )
b10 $
1#
#5380
b0 (
b1101 %
0#
#5390
0"
0'
1!
b0 $
b0 )
1#
#5400
b1 (
b1110 %
0#
#5410
b1 )
0!
b1 $
1#
#5420
1"
1'
b10 (
b1111 %
0#
#5430
b10 $
b10 )
1#
#5440
b0 (
b10000 %
0#
#5450
0"
0'
b0 )
1!
b0 $
1#
#5460
b1 (
b10001 %
0#
#5470
0!
b1 $
b1 )
1#
#5480
1"
1'
b10 (
b10010 %
0#
#5490
b10 )
b10 $
1#
#5500
b0 (
b10011 %
0#
#5510
0"
0'
1!
b0 $
b0 )
1#
#5520
b1 (
b10100 %
0#
#5530
b1 )
0!
b1 $
1#
#5540
1"
1'
b10 (
b10101 %
0#
#5550
b10 $
b10 )
1#
#5560
b0 (
b10110 %
0#
#5570
0"
0'
b0 )
1!
b0 $
1#
#5580
b1 (
b10111 %
0#
#5590
0!
b1 $
b1 )
1#
#5600
1"
1'
b10 (
b11000 %
0#
#5610
b10 )
b10 $
1#
#5620
b0 (
b11001 %
0#
#5630
0"
0'
1!
b0 $
b0 )
1#
#5640
b1 (
b11010 %
0#
#5650
b1 )
0!
b1 $
1#
#5660
1"
1'
b10 (
b11011 %
0#
#5670
b10 $
b10 )
1#
#5680
b0 (
b11100 %
0#
#5690
0"
0'
b0 )
1!
b0 $
1#
#5700
b1 (
b11101 %
0#
#5710
0!
b1 $
b1 )
1#
#5720
1"
1'
b10 (
b11110 %
0#
#5730
b10 )
b10 $
1#
#5740
b0 (
b11111 %
0#
#5750
0"
0'
1!
b0 $
b0 )
1#
#5760
b1 (
b100000 %
0#
#5770
b1 )
0!
b1 $
1#
#5780
1"
1'
b10 (
b100001 %
0#
#5790
b10 $
b10 )
1#
#5800
b0 (
b100010 %
0#
#5810
0"
0'
b0 )
1!
b0 $
1#
#5820
b1 (
b100011 %
0#
#5830
0!
b1 $
b1 )
1#
#5840
1"
1'
b10 (
b100100 %
0#
#5850
b10 )
b10 $
1#
#5860
b0 (
b100101 %
0#
#5870
0"
0'
1!
b0 $
b0 )
1#
#5880
b1 (
b100110 %
0#
#5890
b1 )
0!
b1 $
1#
#5900
1"
1'
b10 (
b100111 %
0#
#5910
b10 $
b10 )
1#
#5920
b0 (
b101000 %
0#
#5930
0"
0'
b0 )
1!
b0 $
1#
#5940
b1 (
b101001 %
0#
#5950
0!
b1 $
b1 )
1#
#5960
1"
1'
b10 (
b101010 %
0#
#5970
b10 )
b10 $
1#
#5980
b0 (
b101011 %
0#
#5990
0"
0'
1!
b0 $
b0 )
1#
#6000
b1 (
b101100 %
0#
#6010
b1 )
0!
b1 $
1#
#6020
1"
1'
b10 (
b101101 %
0#
#6030
b10 $
b10 )
1#
#6040
b0 (
b101110 %
0#
#6050
0"
0'
b0 )
1!
b0 $
1#
#6060
b1 (
b101111 %
0#
#6070
0!
b1 $
b1 )
1#
#6080
1"
1'
b10 (
b110000 %
0#
#6090
b10 )
b10 $
1#
#6100
b0 (
b110001 %
0#
#6110
0"
0'
1!
b0 $
b0 )
1#
#6120
b1 (
b110010 %
0#
#6130
b1 )
0!
b1 $
1#
#6140
1"
1'
b10 (
b110011 %
0#
#6150
b10 $
b10 )
1#
#6160
b0 (
b110100 %
0#
#6170
0"
0'
b0 )
1!
b0 $
1#
#6180
b1 (
b110101 %
0#
#6190
0!
b1 $
b1 )
1#
#6200
1"
1'
b10 (
b110110 %
0#
#6210
b10 )
b10 $
1#
#6220
b0 (
b110111 %
0#
#6230
0"
0'
1!
b0 $
b0 )
1#
#6240
b1 (
b111000 %
0#
#6250
b1 )
0!
b1 $
1#
#6260
1"
1'
b10 (
b111001 %
0#
#6270
b10 $
b10 )
1#
#6280
b0 (
b111010 %
0#
#6290
0"
0'
b0 )
1!
b0 $
1#
#6300
b1 (
b111011 %
0#
#6310
0!
b1 $
b1 )
1#
#6320
1"
1'
b10 (
b111100 %
0#
#6330
b10 )
b10 $
1#
#6340
b0 (
b111101 %
0#
#6350
0"
0'
1!
b0 $
b0 )
1#
#6360
b1 (
b111110 %
0#
#6370
b1 )
0!
b1 $
1#
#6380
1"
1'
b10 (
b111111 %
0#
#6390
b10 $
b10 )
1#
#6400
b0 (
b1000000 %
0#
#6410
0"
0'
b0 )
1!
b0 $
1#
#6420
b1 (
b1000001 %
0#
#6430
0!
b1 $
b1 )
1#
#6440
1"
1'
b10 (
b1000010 %
0#
#6450
b10 )
b10 $
1#
#6460
b0 (
b1000011 %
0#
#6470
0"
0'
1!
b0 $
b0 )
1#
#6480
b1 (
b1000100 %
0#
#6490
b1 )
0!
b1 $
1#
#6500
1"
1'
b10 (
b1000101 %
0#
#6510
b10 $
b10 )
1#
#6520
b0 (
b1000110 %
0#
#6530
0"
0'
b0 )
1!
b0 $
1#
#6540
b1 (
b1000111 %
0#
#6550
0!
b1 $
b1 )
1#
#6560
1"
1'
b10 (
b1001000 %
0#
#6570
b10 )
b10 $
1#
#6580
b0 (
b1001001 %
0#
#6590
0"
0'
1!
b0 $
b0 )
1#
#6600
b1 (
b1001010 %
0#
#6610
b1 )
0!
b1 $
1#
#6620
1"
1'
b10 (
b1001011 %
0#
#6630
b10 $
b10 )
1#
#6640
b0 (
b1001100 %
0#
