benches/clk_domains/Data_CrossDomain.v
module Data_CrossDomain(
    input clkA,
    input FlagIn_clkA, 
    input clkB,
    output FlagOut_clkB,
	input [7:0] dataA,
	output [7:0] dataB
);

// this changes level when the FlagIn_clkA is seen in clkA
reg FlagToggle_clkA;
initial FlagToggle_clkA <= 0;
always @(posedge clkA) FlagToggle_clkA <= FlagToggle_clkA ^ FlagIn_clkA;

reg [7:0] clkA_data;
initial clkA_data <= 8'd0;
always @(posedge clkA) begin
	if (FlagIn_clkA) begin
		clkA_data <= dataA;
	end
end

reg [7:0] clkB_data;
initial clkB_data <= 8'd0;

// which can then be sync-ed to clkB
reg [2:0] SyncA_clkB;
initial SyncA_clkB<=3'b000;
always @(posedge clkB) SyncA_clkB <= {SyncA_clkB[1:0], FlagToggle_clkA};

always @(posedge clkB) begin
	if (SyncA_clkB[1] ^ SyncA_clkB[0]) begin
		clkB_data <= clkA_data;
	end
end

assign dataB = clkB_data;

// and recreate the flag in clkB
assign FlagOut_clkB = (SyncA_clkB[2] ^ SyncA_clkB[1]);

endmodule

benches/clk_domains/testbench.v
module testbench();

reg clkA;
reg clkB;
reg flagIN;
reg [7:0] dataIN;

initial begin
    $dumpfile("bench.vcd");
    $dumpvars(0,testbench);

    $display("starting testbench!!!!");
	
	
	clkB <= 0; 
	repeat (20) begin
		#571;
		clkB <= 1;
		#571;
		clkB <= 0; 
	end
	
    $display("finished OK!");
    $finish;
end

initial begin
	clkA <= 0; 

	repeat (20*29) begin
		#20;
		clkA <= 1;
		#20;
		clkA <= 0; 
	end
end

initial begin
	dataIN <= 8'd0;
	flagIN <= 0;
	#180;
	dataIN <= 8'd066;
	flagIN <= 1;
	#40;
	dataIN <= 8'd0;
	flagIN <= 0;
	#7000;
	dataIN <= 8'd0120;
	flagIN <= 1;
	#40;
	dataIN <= 8'd0;
	flagIN <= 0;
end

wire flagOut;
wire  [7:0] dataOUT;
Data_CrossDomain fck(clkA, flagIN, clkB, flagOut, dataIN, dataOUT);
	
endmodule

benches/clk_domains/bench.vcd
$date
	Sun Oct 25 21:58:42 2015
$end
$version
	Icarus Verilog
$end
$timescale
	1s
$end
$scope module testbench $end
$var wire 1 ! flagOut $end
$var wire 8 " dataOUT [7:0] $end
$var reg 1 # clkA $end
$var reg 1 $ clkB $end
$var reg 8 % dataIN [7:0] $end
$var reg 1 & flagIN $end
$scope module fck $end
$var wire 1 & FlagIn_clkA $end
$var wire 1 ! FlagOut_clkB $end
$var wire 1 # clkA $end
$var wire 1 $ clkB $end
$var wire 8 ' dataA [7:0] $end
$var wire 8 ( dataB [7:0] $end
$var reg 1 ) FlagToggle_clkA $end
$var reg 3 * SyncA_clkB [2:0] $end
$var reg 8 + clkA_data [7:0] $end
$var reg 8 , clkB_data [7:0] $end
$upscope $end
$upscope $end
$enddefinitions $end
#0
$dumpvars
b0 ,
b0 +
b0 *
0)
b0 (
b0 '
0&
b0 %
0$
0#
b0 "
0!
$end
#20
1#
#40
0#
#60
1#
#80
0#
#100
1#
#120
0#
#140
1#
#160
0#
#180
1)
b1000010 +
1#
1&
b1000010 %
b1000010 '
#200
0#
#220
1#
0&
b0 %
b0 '
#240
0#
#260
1#
#280
0#
#300
1#
#320
0#
#340
1#
#360
0#
#380
1#
#400
0#
#420
1#
#440
0#
#460
1#
#480
0#
#500
1#
#520
0#
#540
1#
#560
0#
#571
b1 *
1$
#580
1#
#600
0#
#620
1#
#640
0#
#660
1#
#680
0#
#700
1#
#720
0#
#740
1#
#760
0#
#780
1#
#800
0#
#820
1#
#840
0#
#860
1#
#880
0#
#900
1#
#920
0#
#940
1#
#960
0#
#980
1#
#1000
0#
#1020
1#
#1040
0#
#1060
1#
#1080
0#
#1100
1#
#1120
0#
#1140
1#
#1142
0$
#1160
0#
#1180
1#
#1200
0#
#1220
1#
#1240
0#
#1260
1#
#1280
0#
#1300
1#
#1320
0#
#1340
1#
#1360
0#
#1380
1#
#1400
0#
#1420
1#
#1440
0#
#1460
1#
#1480
0#
#1500
1#
#1520
0#
#1540
1#
#1560
0#
#1580
1#
#1600
0#
#1620
1#
#1640
0#
#1660
1#
#1680
0#
#1700
1#
#1713
1!
b1000010 "
b1000010 (
b1000010 ,
b11 *
1$
#1720
0#
#1740
1#
#1760
0#
#1780
1#
#1800
0#
#1820
1#
#1840
0#
#1860
1#
#1880
0#
#1900
1#
#1920
0#
#1940
1#
#1960
0#
#1980
1#
#2000
0#
#2020
1#
#2040
0#
#2060
1#
#2080
0#
#2100
1#
#2120
0#
#2140
1#
#2160
0#
#2180
1#
#2200
0#
#2220
1#
#2240
0#
#2260
1#
#2280
0#
#2284
0$
#2300
1#
#2320
0#
#2340
1#
#2360
0#
#2380
1#
#2400
0#
#2420
1#
#2440
0#
#2460
1#
#2480
0#
#2500
1#
#2520
0#
#2540
1#
#2560
0#
#2580
1#
#2600
0#
#2620
1#
#2640
0#
#2660
1#
#2680
0#
#2700
1#
#2720
0#
#2740
1#
#2760
0#
#2780
1#
#2800
0#
#2820
1#
#2840
0#
#2855
0!
b111 *
1$
#2860
1#
#2880
0#
#2900
1#
#2920
0#
#2940
1#
#2960
0#
#2980
1#
#3000
0#
#3020
1#
#3040
0#
#3060
1#
#3080
0#
#3100
1#
#3120
0#
#3140
1#
#3160
0#
#3180
1#
#3200
0#
#3220
1#
#3240
0#
#3260
1#
#3280
0#
#3300
1#
#3320
0#
#3340
1#
#3360
0#
#3380
1#
#3400
0#
#3420
1#
#3426
0$
#3440
0#
#3460
1#
#3480
0#
#3500
1#
#3520
0#
#3540
1#
#3560
0#
#3580
1#
#3600
0#
#3620
1#
#3640
0#
#3660
1#
#3680
0#
#3700
1#
#3720
0#
#3740
1#
#3760
0#
#3780
1#
#3800
0#
#3820
1#
#3840
0#
#3860
1#
#3880
0#
#3900
1#
#3920
0#
#3940
1#
#3960
0#
#3980
1#
#3997
1$
#4000
0#
#4020
1#
#4040
0#
#4060
1#
#4080
0#
#4100
1#
#4120
0#
#4140
1#
#4160
0#
#4180
1#
#4200
0#
#4220
1#
#4240
0#
#4260
1#
#4280
0#
#4300
1#
#4320
0#
#4340
1#
#4360
0#
#4380
1#
#4400
0#
#4420
1#
#4440
0#
#4460
1#
#4480
0#
#4500
1#
#4520
0#
#4540
1#
#4560
0#
#4568
0$
#4580
1#
#4600
0#
#4620
1#
#4640
0#
#4660
1#
#4680
0#
#4700
1#
#4720
0#
#4740
1#
#4760
0#
#4780
1#
#4800
0#
#4820
1#
#4840
0#
#4860
1#
#4880
0#
#4900
1#
#4920
0#
#4940
1#
#4960
0#
#4980
1#
#5000
0#
#5020
1#
#5040
0#
#5060
1#
#5080
0#
#5100
1#
#5120
0#
#5139
1$
#5140
1#
#5160
0#
#5180
1#
#5200
0#
#5220
1#
#5240
0#
#5260
1#
#5280
0#
#5300
1#
#5320
0#
#5340
1#
#5360
0#
#5380
1#
#5400
0#
#5420
1#
#5440
0#
#5460
1#
#5480
0#
#5500
1#
#5520
0#
#5540
1#
#5560
0#
#5580
1#
#5600
0#
#5620
1#
#5640
0#
#5660
1#
#5680
0#
#5700
1#
#5710
0$
#5720
0#
#5740
1#
#5760
0#
#5780
1#
#5800
0#
#5820
1#
#5840
0#
#5860
1#
#5880
0#
#5900
1#
#5920
0#
#5940
1#
#5960
0#
#5980
1#
#6000
0#
#6020
1#
#6040
0#
#6060
1#
#6080
0#
#6100
1#
#6120
0#
#6140
1#
#6160
0#
#6180
1#
#6200
0#
#6220
1#
#6240
0#
#6260
1#
#6280
0#
#6281
1$
#6300
1#
#6320
0#
#6340
1#
#6360
0#
#6380
1#
#6400
0#
#6420
1#
#6440
0#
#6460
1#
#6480
0#
#6500
1#
#6520
0#
#6540
1#
#6560
0#
#6580
1#
#6600
0#
#6620
1#
#6640
0#
#6660
1#
#6680
0#
#6700
1#
#6720
0#
#6740
1#
#6760
0#
#6780
1#
#6800
0#
#6820
1#
#6840
0#
#6852
0$
#6860
1#
#6880
0#
#6900
1#
#6920
0#
#6940
1#
#6960
0#
#6980
1#
#7000
0#
#7020
1#
#7040
0#
#7060
1#
#7080
0#
#7100
1#
#7120
0#
#7140
1#
#7160
0#
#7180
1#
#7200
0#
#7220
0)
b1111000 +
1#
1&
b1111000 %
b1111000 '
#7240
0#
#7260
1#
0&
b0 %
b0 '
#7280
0#
#7300
1#
#7320
0#
#7340
1#
#7360
0#
#7380
1#
#7400
0#
#7420
1#
#7423
b110 *
1$
